{"qbedwar": [{"id": 11960, "mc": 29457, "oc": 2452}], "qbcrusher": [{"id": 18534, "mc": 276, "oc": 42}], "qbde": [{"id": 68675, "mc": 8, "oc": 1}], "qbdown": [{"id": 75662, "mc": 432, "oc": 53}], "qbossnft": [{"id": 80352, "mc": 4911, "oc": 112}], "qboi5433": [{"id": 98977, "mc": 3, "oc": 0}], "qb420": [{"id": 118927, "mc": 139, "oc": 18}], "qbcorestore": [{"id": 123547, "mc": 269, "oc": 27}], "qbi8401": [{"id": 138166, "mc": 50, "oc": 5}], "qbism0754": [{"id": 175325, "mc": 12, "oc": 0}], "qbieshay": [{"id": 190371, "mc": 1890, "oc": 635}]}