{"event": [{"id": 707, "mc": 2308, "oc": 104}, {"id": 1681, "mc": 2104, "oc": 120}, {"id": 2215, "mc": 144, "oc": 34}, {"id": 2716, "mc": 101205, "oc": 20512}, {"id": 2727, "mc": 585, "oc": 143}, {"id": 2821, "mc": 106, "oc": 27}, {"id": 2870, "mc": 83131, "oc": 4897}, {"id": 4013, "mc": 159, "oc": 47}, {"id": 4464, "mc": 87, "oc": 29}, {"id": 5178, "mc": 226, "oc": 35}, {"id": 5385, "mc": 113, "oc": 17}, {"id": 7536, "mc": 818, "oc": 102}, {"id": 7637, "mc": 353, "oc": 74}, {"id": 7647, "mc": 5031, "oc": 1467}, {"id": 7648, "mc": 367, "oc": 21}, {"id": 8977, "mc": 1244, "oc": 338}, {"id": 9529, "mc": 2655, "oc": 272}, {"id": 10496, "mc": 1582, "oc": 145}, {"id": 10850, "mc": 167, "oc": 22}, {"id": 11260, "mc": 173, "oc": 38}, {"id": 11616, "mc": 391, "oc": 62}, {"id": 12230, "mc": 1871, "oc": 359}, {"id": 12274, "mc": 21045, "oc": 5436}, {"id": 12337, "mc": 3368, "oc": 196}, {"id": 12964, "mc": 6147, "oc": 2024}, {"id": 13100, "mc": 2092, "oc": 99}, {"id": 14044, "mc": 1096, "oc": 63}, {"id": 14880, "mc": 3338, "oc": 881}, {"id": 15706, "mc": 945, "oc": 281}, {"id": 17562, "mc": 31, "oc": 4}, {"id": 17785, "mc": 28231, "oc": 1075}, {"id": 18837, "mc": 744, "oc": 218}, {"id": 19052, "mc": 163, "oc": 54}, {"id": 19175, "mc": 1452, "oc": 646}, {"id": 19300, "mc": 917, "oc": 201}, {"id": 19866, "mc": 479, "oc": 29}, {"id": 20267, "mc": 91, "oc": 35}, {"id": 20437, "mc": 9010, "oc": 1126}, {"id": 21067, "mc": 133, "oc": 20}, {"id": 21508, "mc": 154, "oc": 22}, {"id": 21520, "mc": 117072, "oc": 5239}, {"id": 22406, "mc": 3299, "oc": 825}, {"id": 23171, "mc": 3266, "oc": 322}, {"id": 23668, "mc": 369, "oc": 33}, {"id": 23730, "mc": 23879, "oc": 4026}, {"id": 24594, "mc": 8959, "oc": 2812}, {"id": 24622, "mc": 127, "oc": 61}, {"id": 25584, "mc": 67039, "oc": 10918}, {"id": 27357, "mc": 15923, "oc": 2322}, {"id": 27427, "mc": 403, "oc": 45}, {"id": 28423, "mc": 9823, "oc": 1626}, {"id": 28594, "mc": 36175, "oc": 2040}, {"id": 28909, "mc": 579, "oc": 119}, {"id": 30733, "mc": 90886, "oc": 8067}, {"id": 31138, "mc": 17359, "oc": 4499}, {"id": 31459, "mc": 5991, "oc": 1220}, {"id": 33672, "mc": 7582, "oc": 192}, {"id": 33808, "mc": 5182, "oc": 795}, {"id": 33939, "mc": 1239, "oc": 286}, {"id": 33939, "mc": 1239, "oc": 286}, {"id": 33939, "mc": 1239, "oc": 286}, {"id": 34331, "mc": 25394, "oc": 3587}, {"id": 34750, "mc": 158698, "oc": 7124}, {"id": 35081, "mc": 580, "oc": 94}, {"id": 36737, "mc": 1238, "oc": 335}, {"id": 37222, "mc": 796, "oc": 89}, {"id": 37554, "mc": 286, "oc": 85}, {"id": 37833, "mc": 867, "oc": 92}, {"id": 37986, "mc": 741, "oc": 177}, {"id": 38155, "mc": 144, "oc": 26}, {"id": 38401, "mc": 8389, "oc": 818}, {"id": 38970, "mc": 4655, "oc": 870}, {"id": 39277, "mc": 1939, "oc": 88}, {"id": 39650, "mc": 5678, "oc": 749}, {"id": 39887, "mc": 105, "oc": 39}, {"id": 39990, "mc": 791, "oc": 60}, {"id": 41854, "mc": 1254, "oc": 59}, {"id": 43833, "mc": 1997, "oc": 179}, {"id": 43977, "mc": 2350, "oc": 256}, {"id": 44076, "mc": 47, "oc": 11}, {"id": 45204, "mc": 904, "oc": 212}, {"id": 45367, "mc": 369, "oc": 83}, {"id": 45633, "mc": 18379, "oc": 1178}, {"id": 45988, "mc": 23213, "oc": 545}, {"id": 46079, "mc": 2234, "oc": 628}, {"id": 46543, "mc": 39, "oc": 7}, {"id": 46682, "mc": 2590, "oc": 312}, {"id": 46856, "mc": 185, "oc": 38}, {"id": 47541, "mc": 1165, "oc": 292}, {"id": 47838, "mc": 771, "oc": 68}, {"id": 48712, "mc": 513, "oc": 188}, {"id": 48849, "mc": 7475, "oc": 2680}, {"id": 49014, "mc": 62827, "oc": 10276}, {"id": 49335, "mc": 7247, "oc": 1266}, {"id": 51593, "mc": 204, "oc": 44}, {"id": 51744, "mc": 1666, "oc": 303}, {"id": 52300, "mc": 18716, "oc": 54}, {"id": 52310, "mc": 263, "oc": 78}, {"id": 54900, "mc": 222, "oc": 53}, {"id": 54963, "mc": 192, "oc": 58}, {"id": 55425, "mc": 747, "oc": 119}, {"id": 55460, "mc": 56283, "oc": 11112}, {"id": 56604, "mc": 6665, "oc": 775}, {"id": 57078, "mc": 294, "oc": 39}, {"id": 58884, "mc": 475, "oc": 119}, {"id": 59576, "mc": 133, "oc": 47}, {"id": 59774, "mc": 2551, "oc": 218}, {"id": 60109, "mc": 109455, "oc": 21736}, {"id": 60187, "mc": 5221, "oc": 1256}, {"id": 60589, "mc": 58, "oc": 19}, {"id": 61262, "mc": 57, "oc": 29}, {"id": 61789, "mc": 301, "oc": 70}, {"id": 61821, "mc": 236, "oc": 51}, {"id": 62022, "mc": 409, "oc": 55}, {"id": 62043, "mc": 1102, "oc": 316}, {"id": 62525, "mc": 524, "oc": 137}, {"id": 62632, "mc": 52902, "oc": 5804}, {"id": 62642, "mc": 576, "oc": 145}, {"id": 63103, "mc": 735, "oc": 121}, {"id": 63272, "mc": 3189, "oc": 711}, {"id": 63338, "mc": 1966, "oc": 251}, {"id": 63548, "mc": 17, "oc": 5}, {"id": 64948, "mc": 174597, "oc": 16120}, {"id": 65123, "mc": 25823, "oc": 9719}, {"id": 65523, "mc": 15, "oc": 14}, {"id": 65863, "mc": 2998, "oc": 1599}, {"id": 66619, "mc": 219, "oc": 90}, {"id": 66651, "mc": 724, "oc": 114}, {"id": 69441, "mc": 6856, "oc": 1808}, {"id": 70670, "mc": 1637, "oc": 202}, {"id": 71122, "mc": 2049, "oc": 97}, {"id": 71273, "mc": 89, "oc": 36}, {"id": 73680, "mc": 272, "oc": 122}, {"id": 74367, "mc": 2103, "oc": 366}, {"id": 74385, "mc": 100, "oc": 60}, {"id": 74395, "mc": 225, "oc": 43}, {"id": 74821, "mc": 103, "oc": 27}, {"id": 76273, "mc": 2635, "oc": 104}, {"id": 76310, "mc": 196, "oc": 94}, {"id": 76463, "mc": 141596, "oc": 42802}, {"id": 76644, "mc": 158, "oc": 47}, {"id": 77155, "mc": 560, "oc": 186}, {"id": 77374, "mc": 12591, "oc": 2737}, {"id": 77788, "mc": 1806, "oc": 189}, {"id": 77812, "mc": 578, "oc": 134}, {"id": 78279, "mc": 131, "oc": 32}, {"id": 78719, "mc": 3170, "oc": 610}, {"id": 79423, "mc": 19542, "oc": 1854}, {"id": 79807, "mc": 398, "oc": 62}, {"id": 80292, "mc": 19722, "oc": 1782}, {"id": 82139, "mc": 111, "oc": 35}, {"id": 82615, "mc": 282, "oc": 57}, {"id": 82968, "mc": 1154, "oc": 275}, {"id": 82996, "mc": 2862, "oc": 158}, {"id": 83376, "mc": 1114, "oc": 79}, {"id": 84521, "mc": 2731, "oc": 363}, {"id": 84802, "mc": 875, "oc": 197}, {"id": 84823, "mc": 11357, "oc": 2097}, {"id": 85622, "mc": 10080, "oc": 270}, {"id": 85641, "mc": 422486, "oc": 126473}, {"id": 86632, "mc": 212452, "oc": 25450}, {"id": 87328, "mc": 76448, "oc": 19683}, {"id": 87571, "mc": 1103, "oc": 168}, {"id": 88295, "mc": 780, "oc": 147}, {"id": 90083, "mc": 99746, "oc": 11366}, {"id": 91182, "mc": 73, "oc": 24}, {"id": 91442, "mc": 620, "oc": 102}, {"id": 91687, "mc": 1064, "oc": 131}, {"id": 92141, "mc": 128, "oc": 30}, {"id": 93142, "mc": 89, "oc": 15}, {"id": 93263, "mc": 1118, "oc": 270}, {"id": 93320, "mc": 1140, "oc": 194}, {"id": 93908, "mc": 100, "oc": 26}, {"id": 94024, "mc": 99, "oc": 14}, {"id": 94867, "mc": 409, "oc": 97}, {"id": 94877, "mc": 163763, "oc": 9240}, {"id": 95248, "mc": 10209, "oc": 711}, {"id": 95437, "mc": 429, "oc": 48}, {"id": 96001, "mc": 710, "oc": 109}, {"id": 96621, "mc": 87, "oc": 18}, {"id": 96785, "mc": 51353, "oc": 3561}, {"id": 96807, "mc": 779, "oc": 128}, {"id": 97801, "mc": 16341, "oc": 5386}, {"id": 97818, "mc": 85, "oc": 7}, {"id": 98150, "mc": 118, "oc": 11}, {"id": 98989, "mc": 113, "oc": 29}, {"id": 99246, "mc": 21230, "oc": 2178}, {"id": 100030, "mc": 690, "oc": 74}, {"id": 100318, "mc": 3667, "oc": 689}, {"id": 101032, "mc": 137280, "oc": 22310}, {"id": 104656, "mc": 49, "oc": 11}, {"id": 105374, "mc": 2986, "oc": 209}, {"id": 106163, "mc": 882, "oc": 202}, {"id": 106433, "mc": 336, "oc": 53}, {"id": 108151, "mc": 79, "oc": 34}, {"id": 108560, "mc": 102872, "oc": 3877}, {"id": 109485, "mc": 7303, "oc": 1961}, {"id": 109835, "mc": 1834, "oc": 513}, {"id": 111591, "mc": 6444, "oc": 1001}, {"id": 111813, "mc": 4236, "oc": 1006}, {"id": 111965, "mc": 2702, "oc": 302}, {"id": 113403, "mc": 2972, "oc": 709}, {"id": 113881, "mc": 118, "oc": 34}, {"id": 114115, "mc": 573, "oc": 138}, {"id": 115830, "mc": 314, "oc": 45}, {"id": 116544, "mc": 3900, "oc": 578}, {"id": 118030, "mc": 94956, "oc": 1701}, {"id": 118552, "mc": 293, "oc": 43}, {"id": 119748, "mc": 777, "oc": 204}, {"id": 120592, "mc": 212, "oc": 37}, {"id": 120817, "mc": 2477, "oc": 247}, {"id": 121719, "mc": 524, "oc": 255}, {"id": 122283, "mc": 5443, "oc": 251}, {"id": 122814, "mc": 19476, "oc": 3657}, {"id": 123097, "mc": 9377, "oc": 688}, {"id": 123911, "mc": 28754, "oc": 5535}, {"id": 123954, "mc": 68, "oc": 18}, {"id": 123980, "mc": 930, "oc": 215}, {"id": 124758, "mc": 90, "oc": 31}, {"id": 126661, "mc": 819, "oc": 160}, {"id": 126885, "mc": 1108, "oc": 248}, {"id": 127677, "mc": 22, "oc": 12}, {"id": 128192, "mc": 4614, "oc": 1356}, {"id": 129632, "mc": 4887, "oc": 1876}, {"id": 129737, "mc": 6073, "oc": 1109}, {"id": 131316, "mc": 121, "oc": 27}, {"id": 132066, "mc": 3098, "oc": 1085}, {"id": 132451, "mc": 6102, "oc": 2993}, {"id": 132569, "mc": 157, "oc": 62}, {"id": 132688, "mc": 489, "oc": 93}, {"id": 132768, "mc": 1883, "oc": 160}, {"id": 132863, "mc": 21, "oc": 4}, {"id": 132892, "mc": 3360, "oc": 519}, {"id": 133643, "mc": 194, "oc": 56}, {"id": 133772, "mc": 22627, "oc": 7265}, {"id": 133952, "mc": 2695, "oc": 736}, {"id": 135237, "mc": 977, "oc": 44}, {"id": 135380, "mc": 39, "oc": 19}, {"id": 136469, "mc": 144, "oc": 96}, {"id": 137619, "mc": 180, "oc": 57}, {"id": 138796, "mc": 115, "oc": 55}, {"id": 141225, "mc": 3036, "oc": 344}, {"id": 141357, "mc": 849, "oc": 138}, {"id": 142297, "mc": 2871, "oc": 159}, {"id": 145904, "mc": 4728, "oc": 317}, {"id": 145955, "mc": 297, "oc": 60}, {"id": 146296, "mc": 5045, "oc": 298}, {"id": 147433, "mc": 19195, "oc": 843}, {"id": 147459, "mc": 54086, "oc": 5102}, {"id": 150948, "mc": 94, "oc": 19}, {"id": 150995, "mc": 1573, "oc": 22}, {"id": 152008, "mc": 294, "oc": 22}, {"id": 152120, "mc": 2779, "oc": 187}, {"id": 152147, "mc": 72, "oc": 11}, {"id": 152756, "mc": 684, "oc": 33}, {"id": 154389, "mc": 152, "oc": 56}, {"id": 154425, "mc": 25566, "oc": 1967}, {"id": 155541, "mc": 1863, "oc": 660}, {"id": 155656, "mc": 586, "oc": 74}, {"id": 155879, "mc": 432, "oc": 67}, {"id": 156433, "mc": 168, "oc": 14}, {"id": 158577, "mc": 740, "oc": 126}, {"id": 159671, "mc": 8736, "oc": 1804}, {"id": 160343, "mc": 189, "oc": 14}, {"id": 161374, "mc": 15710, "oc": 3025}, {"id": 161838, "mc": 2983, "oc": 574}, {"id": 161875, "mc": 152, "oc": 31}, {"id": 162965, "mc": 3509, "oc": 143}, {"id": 163439, "mc": 24, "oc": 7}, {"id": 164318, "mc": 1072, "oc": 133}, {"id": 164905, "mc": 2375, "oc": 179}, {"id": 165066, "mc": 3488, "oc": 233}, {"id": 166160, "mc": 24375, "oc": 6152}, {"id": 166306, "mc": 64247, "oc": 621}, {"id": 166621, "mc": 1415, "oc": 227}, {"id": 166860, "mc": 1576, "oc": 141}, {"id": 167316, "mc": 146, "oc": 37}, {"id": 167318, "mc": 128, "oc": 24}, {"id": 167463, "mc": 122, "oc": 27}, {"id": 168059, "mc": 1199, "oc": 177}, {"id": 168149, "mc": 529, "oc": 77}, {"id": 168164, "mc": 182, "oc": 50}, {"id": 168366, "mc": 2984, "oc": 743}, {"id": 169754, "mc": 2939, "oc": 354}, {"id": 170274, "mc": 14639, "oc": 1382}, {"id": 170636, "mc": 11074, "oc": 942}, {"id": 170653, "mc": 113, "oc": 23}, {"id": 171478, "mc": 111, "oc": 18}, {"id": 171559, "mc": 145, "oc": 31}, {"id": 171774, "mc": 1247, "oc": 141}, {"id": 173010, "mc": 166, "oc": 43}, {"id": 175011, "mc": 300176, "oc": 71581}, {"id": 175213, "mc": 1160, "oc": 156}, {"id": 175661, "mc": 240, "oc": 48}, {"id": 178504, "mc": 116, "oc": 42}, {"id": 180874, "mc": 8432, "oc": 884}, {"id": 181278, "mc": 630, "oc": 100}, {"id": 183823, "mc": 47, "oc": 18}, {"id": 183993, "mc": 1750, "oc": 215}, {"id": 184865, "mc": 5264, "oc": 830}, {"id": 185605, "mc": 343, "oc": 32}, {"id": 185796, "mc": 7374, "oc": 1171}, {"id": 186633, "mc": 10636, "oc": 1159}, {"id": 187102, "mc": 9045, "oc": 2842}, {"id": 187857, "mc": 90, "oc": 12}, {"id": 189180, "mc": 966, "oc": 369}, {"id": 189455, "mc": 4848, "oc": 334}, {"id": 190610, "mc": 2406, "oc": 169}, {"id": 190866, "mc": 7257, "oc": 1334}, {"id": 191771, "mc": 14094, "oc": 580}, {"id": 192833, "mc": 5433, "oc": 829}, {"id": 193266, "mc": 5215, "oc": 521}, {"id": 193821, "mc": 339, "oc": 91}, {"id": 194739, "mc": 8346, "oc": 1363}, {"id": 195654, "mc": 545, "oc": 96}, {"id": 195963, "mc": 166, "oc": 20}, {"id": 196344, "mc": 3386, "oc": 290}, {"id": 197028, "mc": 1216, "oc": 219}, {"id": 198349, "mc": 13252, "oc": 2199}, {"id": 198379, "mc": 2115, "oc": 235}, {"id": 198862, "mc": 243, "oc": 22}, {"id": 198913, "mc": 146, "oc": 26}, {"id": 199103, "mc": 243, "oc": 36}], "evento": [{"id": 1573, "mc": 546, "oc": 180}, {"id": 1639, "mc": 779, "oc": 89}, {"id": 8035, "mc": 889, "oc": 504}, {"id": 9524, "mc": 2461, "oc": 256}, {"id": 10539, "mc": 282, "oc": 60}, {"id": 15781, "mc": 32, "oc": 18}, {"id": 17235, "mc": 754, "oc": 48}, {"id": 21808, "mc": 56664, "oc": 2750}, {"id": 24184, "mc": 9672, "oc": 2100}, {"id": 33006, "mc": 9, "oc": 6}, {"id": 33870, "mc": 1100, "oc": 145}, {"id": 41708, "mc": 675, "oc": 83}, {"id": 44875, "mc": 352, "oc": 37}, {"id": 48234, "mc": 159, "oc": 38}, {"id": 54514, "mc": 187, "oc": 55}, {"id": 55147, "mc": 318, "oc": 89}, {"id": 55877, "mc": 2243, "oc": 606}, {"id": 62573, "mc": 1279, "oc": 82}, {"id": 64142, "mc": 2183, "oc": 233}, {"id": 68672, "mc": 8, "oc": 2}, {"id": 80093, "mc": 59, "oc": 15}, {"id": 94177, "mc": 18623, "oc": 662}, {"id": 97229, "mc": 563, "oc": 33}, {"id": 98793, "mc": 1070, "oc": 163}, {"id": 98938, "mc": 240990, "oc": 5482}, {"id": 105784, "mc": 70, "oc": 23}, {"id": 122338, "mc": 295, "oc": 43}, {"id": 125740, "mc": 663, "oc": 121}, {"id": 126049, "mc": 3194, "oc": 527}, {"id": 126669, "mc": 121, "oc": 27}, {"id": 130201, "mc": 2110, "oc": 384}, {"id": 134357, "mc": 2411, "oc": 237}, {"id": 148893, "mc": 1305, "oc": 504}, {"id": 154975, "mc": 35, "oc": 11}, {"id": 155507, "mc": 15007, "oc": 318}, {"id": 160937, "mc": 1252, "oc": 200}, {"id": 166277, "mc": 2014, "oc": 325}, {"id": 167902, "mc": 126, "oc": 14}, {"id": 171636, "mc": 21620, "oc": 2075}, {"id": 180626, "mc": 125, "oc": 20}, {"id": 194012, "mc": 1070, "oc": 157}], "evan": [{"id": 14259, "mc": 186, "oc": 27}, {"id": 145258, "mc": 23, "oc": 7}], "evil": [{"id": 14639, "mc": 421, "oc": 79}, {"id": 27402, "mc": 117, "oc": 59}, {"id": 57582, "mc": 83, "oc": 51}, {"id": 63689, "mc": 2166, "oc": 570}, {"id": 63797, "mc": 23, "oc": 14}, {"id": 64768, "mc": 184, "oc": 37}, {"id": 69520, "mc": 221, "oc": 49}, {"id": 86232, "mc": 98, "oc": 26}, {"id": 93695, "mc": 28, "oc": 8}, {"id": 107927, "mc": 23, "oc": 6}, {"id": 112550, "mc": 1102, "oc": 212}, {"id": 118915, "mc": 10, "oc": 1}, {"id": 122568, "mc": 95, "oc": 38}, {"id": 130524, "mc": 533, "oc": 190}, {"id": 134159, "mc": 172, "oc": 48}, {"id": 134480, "mc": 654, "oc": 124}, {"id": 152791, "mc": 909, "oc": 228}, {"id": 169843, "mc": 24039, "oc": 3717}, {"id": 171224, "mc": 75, "oc": 12}, {"id": 181709, "mc": 368, "oc": 91}], "evolving": [{"id": 18149, "mc": 1690, "oc": 141}, {"id": 183580, "mc": 57, "oc": 10}], "everything": [{"id": 23396, "mc": 127, "oc": 14}, {"id": 48995, "mc": 524, "oc": 125}, {"id": 101462, "mc": 1811, "oc": 166}, {"id": 120231, "mc": 348, "oc": 88}, {"id": 131660, "mc": 94, "oc": 29}, {"id": 148731, "mc": 529, "oc": 101}], "evangelion": [{"id": 25126, "mc": 1481, "oc": 393}], "evolution": [{"id": 32116, "mc": 1508, "oc": 124}, {"id": 196981, "mc": 66935, "oc": 6559}], "ever": [{"id": 43630, "mc": 6, "oc": 1}, {"id": 155929, "mc": 699, "oc": 185}], "even": [{"id": 46087, "mc": 2248, "oc": 766}], "everyone": [{"id": 48883, "mc": 19605, "oc": 3411}, {"id": 79868, "mc": 302, "oc": 38}, {"id": 90038, "mc": 67, "oc": 18}, {"id": 114115, "mc": 573, "oc": 138}, {"id": 116200, "mc": 432, "oc": 84}, {"id": 142108, "mc": 965, "oc": 36}, {"id": 150020, "mc": 117, "oc": 21}, {"id": 155804, "mc": 378, "oc": 48}, {"id": 166203, "mc": 202, "oc": 35}, {"id": 196152, "mc": 189, "oc": 26}, {"id": 196483, "mc": 621, "oc": 108}], "everyhting": [{"id": 48995, "mc": 524, "oc": 125}], "eventful": [{"id": 53686, "mc": 6569, "oc": 838}, {"id": 143303, "mc": 269, "oc": 44}, {"id": 185890, "mc": 5643, "oc": 1892}], "eventy": [{"id": 55631, "mc": 552, "oc": 26}], "evo": [{"id": 61574, "mc": 479, "oc": 54}, {"id": 97818, "mc": 85, "oc": 7}], "ev": [{"id": 79962, "mc": 7245, "oc": 323}], "evolve": [{"id": 100125, "mc": 629, "oc": 122}], "evenement": [{"id": 113665, "mc": 1270, "oc": 199}], "eve": [{"id": 117432, "mc": 388, "oc": 218}], "evony": [{"id": 129883, "mc": 228, "oc": 27}], "evonycompanion": [{"id": 129883, "mc": 228, "oc": 27}], "every": [{"id": 140929, "mc": 59, "oc": 22}], "eventi": [{"id": 156657, "mc": 256, "oc": 17}], "evora": [{"id": 167876, "mc": 1413, "oc": 99}], "evolved": [{"id": 176864, "mc": 887, "oc": 94}], "everquest": [{"id": 183458, "mc": 20970, "oc": 4110}], "evidence": [{"id": 185953, "mc": 241, "oc": 14}], "everybody": [{"id": 196571, "mc": 2693, "oc": 782}, {"id": 196571, "mc": 2693, "oc": 782}]}