{"hnk": [{"id": 32090, "mc": 8315, "oc": 876}], "hnue": [{"id": 36984, "mc": 302, "oc": 32}], "hnu": [{"id": 39653, "mc": 80, "oc": 12}], "hns": [{"id": 45188, "mc": 835, "oc": 59}], "hntservice": [{"id": 72004, "mc": 521, "oc": 18}], "hnvestordao": [{"id": 90940, "mc": 61, "oc": 7}], "hn": [{"id": 91057, "mc": 31, "oc": 8}, {"id": 171762, "mc": 26, "oc": 8}], "hndl": [{"id": 189054, "mc": 211, "oc": 24}], "hncl": [{"id": 190953, "mc": 289, "oc": 27}], "hnt": [{"id": 217569, "mc": 17, "oc": 0}], "hnn": [{"id": 241205, "mc": 1006, "oc": 176}]}