{"fcoughlin": [{"id": 10961, "mc": 2031, "oc": 751}], "fceoft": [{"id": 15687, "mc": 2892, "oc": 17}, {"id": 90536, "mc": 493, "oc": 9}], "fc": [{"id": 25049, "mc": 5362, "oc": 74}, {"id": 26061, "mc": 1396, "oc": 60}, {"id": 32599, "mc": 164, "oc": 44}, {"id": 149877, "mc": 7468, "oc": 895}, {"id": 165591, "mc": 110, "oc": 22}, {"id": 175998, "mc": 28, "oc": 1}], "fck": [{"id": 55946, "mc": 474, "oc": 26}], "fcw": [{"id": 69489, "mc": 26, "oc": 7}, {"id": 142424, "mc": 147, "oc": 41}], "fccview": [{"id": 74983, "mc": 9, "oc": 1}], "fcdoomsday": [{"id": 80592, "mc": 321, "oc": 72}], "fchy": [{"id": 110513, "mc": 930, "oc": 140}], "fcbrown": [{"id": 129057, "mc": 4160, "oc": 133}], "fcc": [{"id": 134982, "mc": 66, "oc": 2}], "fct": [{"id": 146934, "mc": 297, "oc": 19}], "fcs": [{"id": 154305, "mc": 3, "oc": 0}], "fc8m738": [{"id": 199973, "mc": 4593, "oc": 315}]}