{"pfp": [{"id": 30076, "mc": 657, "oc": 52}, {"id": 60769, "mc": 6, "oc": 2}], "pfann": [{"id": 53627, "mc": 567, "oc": 21}], "pfeuffer": [{"id": 55119, "mc": 106, "oc": 3}], "pfister": [{"id": 59399, "mc": 1371, "oc": 130}], "pform": [{"id": 85471, "mc": 6950, "oc": 422}], "pfeiffer": [{"id": 130333, "mc": 2961, "oc": 775}], "pf": [{"id": 144604, "mc": 2, "oc": 1}, {"id": 198817, "mc": 83, "oc": 22}], "pft27": [{"id": 146829, "mc": 132, "oc": 22}], "pfau": [{"id": 152658, "mc": 22128, "oc": 4588}], "pfenix": [{"id": 157344, "mc": 71, "oc": 14}], "pfunkpearl": [{"id": 159554, "mc": 4354, "oc": 854}], "pford": [{"id": 160219, "mc": 29, "oc": 2}], "pfif": [{"id": 171535, "mc": 4, "oc": 4}], "pflaume": [{"id": 190054, "mc": 83, "oc": 11}], "pfm": [{"id": 197365, "mc": 3638, "oc": 564}]}