{"syatyou": [{"id": 610, "mc": 131, "oc": 19}], "syntaxff": [{"id": 649, "mc": 6, "oc": 1}], "synd": [{"id": 766, "mc": 27, "oc": 9}, {"id": 31184, "mc": 10, "oc": 0}], "system": [{"id": 805, "mc": 6, "oc": 3}, {"id": 11936, "mc": 15, "oc": 3}, {"id": 15165, "mc": 26447, "oc": 9356}, {"id": 22477, "mc": 6, "oc": 5}, {"id": 66773, "mc": 11, "oc": 7}, {"id": 76526, "mc": 7, "oc": 1}, {"id": 79670, "mc": 7, "oc": 2}, {"id": 97010, "mc": 68, "oc": 23}, {"id": 114007, "mc": 100, "oc": 25}, {"id": 117665, "mc": 112, "oc": 35}, {"id": 121059, "mc": 1084, "oc": 347}, {"id": 130999, "mc": 27, "oc": 15}, {"id": 146120, "mc": 4471, "oc": 1424}, {"id": 150569, "mc": 669, "oc": 39}, {"id": 156207, "mc": 5, "oc": 0}, {"id": 158306, "mc": 132, "oc": 19}, {"id": 160487, "mc": 971, "oc": 22}, {"id": 192502, "mc": 1, "oc": 0}, {"id": 194231, "mc": 426, "oc": 82}, {"id": 194440, "mc": 1, "oc": 0}], "synthese": [{"id": 824, "mc": 128, "oc": 7}], "syn": [{"id": 1282, "mc": 116, "oc": 28}, {"id": 27171, "mc": 188, "oc": 60}, {"id": 47712, "mc": 6785, "oc": 1307}, {"id": 49350, "mc": 35, "oc": 8}, {"id": 50732, "mc": 59, "oc": 4}, {"id": 67040, "mc": 15, "oc": 5}, {"id": 95201, "mc": 19782, "oc": 2600}, {"id": 142619, "mc": 15288, "oc": 1499}, {"id": 147925, "mc": 27, "oc": 9}, {"id": 173185, "mc": 6, "oc": 4}], "synae": [{"id": 1835, "mc": 32998, "oc": 3754}], "syl": [{"id": 2006, "mc": 502, "oc": 77}, {"id": 28284, "mc": 3, "oc": 0}, {"id": 60453, "mc": 30, "oc": 8}], "symystery": [{"id": 3509, "mc": 2074, "oc": 527}, {"id": 51428, "mc": 37, "oc": 14}], "synergy": [{"id": 5591, "mc": 48, "oc": 20}, {"id": 20427, "mc": 4132, "oc": 781}, {"id": 117728, "mc": 615, "oc": 120}, {"id": 150648, "mc": 177, "oc": 14}, {"id": 158972, "mc": 315, "oc": 15}], "syd": [{"id": 6141, "mc": 589, "oc": 13}, {"id": 11260, "mc": 173, "oc": 38}, {"id": 14514, "mc": 33, "oc": 14}, {"id": 84631, "mc": 4, "oc": 1}, {"id": 89496, "mc": 123, "oc": 14}, {"id": 198492, "mc": 3647, "oc": 57}], "systolichorse": [{"id": 6874, "mc": 13645, "oc": 9}], "sylo": [{"id": 7446, "mc": 292, "oc": 21}], "sylwira": [{"id": 7884, "mc": 7, "oc": 3}], "syouta": [{"id": 8276, "mc": 188, "oc": 42}], "sythsaz": [{"id": 8360, "mc": 18, "oc": 9}], "sylwiaz": [{"id": 8708, "mc": 4041, "oc": 128}], "sylvie": [{"id": 9640, "mc": 69, "oc": 27}, {"id": 19764, "mc": 617, "oc": 73}, {"id": 25543, "mc": 211, "oc": 29}, {"id": 142562, "mc": 117, "oc": 14}], "sylwester": [{"id": 10620, "mc": 59, "oc": 11}], "sylv0": [{"id": 11145, "mc": 5165, "oc": 977}], "syahimhir": [{"id": 11744, "mc": 208, "oc": 15}], "sync": [{"id": 12711, "mc": 65, "oc": 12}, {"id": 58083, "mc": 3155, "oc": 220}, {"id": 75673, "mc": 24, "oc": 8}, {"id": 100754, "mc": 92, "oc": 16}, {"id": 101273, "mc": 114, "oc": 27}, {"id": 154079, "mc": 52, "oc": 11}, {"id": 185793, "mc": 182, "oc": 8}], "sylvaincorte": [{"id": 16026, "mc": 443, "oc": 17}], "syphon": [{"id": 16116, "mc": 254, "oc": 61}], "sys": [{"id": 16268, "mc": 19, "oc": 9}, {"id": 22835, "mc": 150, "oc": 12}, {"id": 51397, "mc": 2539, "oc": 32}, {"id": 134745, "mc": 117, "oc": 17}, {"id": 180887, "mc": 20, "oc": 1}], "synack": [{"id": 16357, "mc": 3225, "oc": 782}, {"id": 75922, "mc": 364, "oc": 117}], "sybil": [{"id": 16677, "mc": 14053, "oc": 45}, {"id": 132573, "mc": 68, "oc": 34}], "syrox": [{"id": 16845, "mc": 366, "oc": 29}], "sylvarix": [{"id": 17495, "mc": 68, "oc": 10}], "sysy": [{"id": 18224, "mc": 2727, "oc": 89}, {"id": 183668, "mc": 316, "oc": 8}], "sydneyqofficial": [{"id": 19150, "mc": 678, "oc": 18}], "syrence": [{"id": 19248, "mc": 109, "oc": 30}], "syndrome": [{"id": 19452, "mc": 4, "oc": 3}], "syle": [{"id": 20592, "mc": 2887, "oc": 37}], "syncora": [{"id": 21299, "mc": 36315, "oc": 1636}], "synaxrider": [{"id": 21870, "mc": 235, "oc": 12}], "syloh": [{"id": 22852, "mc": 278, "oc": 151}], "syntax": [{"id": 23640, "mc": 142, "oc": 38}, {"id": 46804, "mc": 110, "oc": 15}, {"id": 194872, "mc": 972, "oc": 81}], "syuluri": [{"id": 23966, "mc": 1, "oc": 0}], "sykowin": [{"id": 25143, "mc": 809, "oc": 27}], "syla": [{"id": 25812, "mc": 45, "oc": 11}], "syrowatt": [{"id": 25983, "mc": 191, "oc": 24}], "symphonic": [{"id": 26389, "mc": 38, "oc": 9}], "sykz": [{"id": 26543, "mc": 898, "oc": 190}], "sylaise": [{"id": 27940, "mc": 204, "oc": 50}], "synzak": [{"id": 28945, "mc": 4, "oc": 1}], "syama1": [{"id": 29287, "mc": 585, "oc": 38}, {"id": 163679, "mc": 1027, "oc": 22}], "sylwen": [{"id": 31024, "mc": 23, "oc": 4}], "synchrowork": [{"id": 32228, "mc": 112, "oc": 25}], "syxnity": [{"id": 34236, "mc": 33, "oc": 12}], "syfi": [{"id": 34927, "mc": 57, "oc": 9}], "synetic": [{"id": 35269, "mc": 74, "oc": 8}], "synx": [{"id": 36751, "mc": 8154, "oc": 55}, {"id": 109247, "mc": 1204, "oc": 123}, {"id": 152626, "mc": 197, "oc": 10}], "sylvietg": [{"id": 36785, "mc": 17, "oc": 8}, {"id": 199657, "mc": 946, "oc": 117}], "sytri": [{"id": 37033, "mc": 22, "oc": 3}], "syu": [{"id": 37225, "mc": 4, "oc": 1}], "sydneyohko": [{"id": 37675, "mc": 64, "oc": 16}], "syncr0": [{"id": 37687, "mc": 12, "oc": 3}], "syverlauritz": [{"id": 39050, "mc": 71, "oc": 12}], "sygnu": [{"id": 40091, "mc": 1499, "oc": 192}], "sylvarant": [{"id": 40295, "mc": 110757, "oc": 3795}], "sylvy": [{"id": 40744, "mc": 25, "oc": 8}], "sydney": [{"id": 41735, "mc": 162, "oc": 7}, {"id": 46565, "mc": 36221, "oc": 30}, {"id": 77983, "mc": 192, "oc": 9}, {"id": 128421, "mc": 19, "oc": 4}], "symphony": [{"id": 42422, "mc": 2645, "oc": 764}, {"id": 82343, "mc": 4241, "oc": 878}, {"id": 86748, "mc": 2387, "oc": 678}, {"id": 113133, "mc": 129, "oc": 30}], "sylphy": [{"id": 42465, "mc": 64, "oc": 14}], "sybau": [{"id": 45086, "mc": 15, "oc": 3}, {"id": 105935, "mc": 23, "oc": 6}, {"id": 163611, "mc": 33, "oc": 19}], "syrupv": [{"id": 45087, "mc": 1, "oc": 1}], "symatt": [{"id": 45460, "mc": 12, "oc": 1}], "sylv": [{"id": 45485, "mc": 22, "oc": 2}, {"id": 61674, "mc": 14, "oc": 4}, {"id": 134248, "mc": 884, "oc": 198}, {"id": 139576, "mc": 7, "oc": 0}], "sykoco": [{"id": 45491, "mc": 682, "oc": 75}], "synth": [{"id": 47153, "mc": 54, "oc": 15}, {"id": 61691, "mc": 368, "oc": 178}, {"id": 110215, "mc": 9, "oc": 1}, {"id": 171480, "mc": 59, "oc": 4}], "syahrul": [{"id": 48614, "mc": 12, "oc": 2}], "sylko": [{"id": 50751, "mc": 8354, "oc": 2098}], "syrex": [{"id": 51228, "mc": 11731, "oc": 44}, {"id": 140847, "mc": 11, "oc": 3}], "sylph": [{"id": 51505, "mc": 27, "oc": 10}], "syberviel": [{"id": 51851, "mc": 25, "oc": 5}], "sycotic": [{"id": 53537, "mc": 102, "oc": 25}], "syc": [{"id": 53954, "mc": 2279, "oc": 27}], "synk": [{"id": 53956, "mc": 47, "oc": 12}, {"id": 182125, "mc": 9, "oc": 2}], "symbiosi": [{"id": 54791, "mc": 214, "oc": 16}], "sylv3onyt": [{"id": 55703, "mc": 9, "oc": 2}, {"id": 77185, "mc": 1, "oc": 0}], "sylvestre": [{"id": 57858, "mc": 174, "oc": 23}, {"id": 141990, "mc": 122, "oc": 24}], "sylveer": [{"id": 57962, "mc": 2020, "oc": 41}], "sydni": [{"id": 59197, "mc": 128, "oc": 15}], "synvak": [{"id": 59519, "mc": 16, "oc": 3}], "syaly": [{"id": 60475, "mc": 54, "oc": 0}], "syaiton": [{"id": 62437, "mc": 773, "oc": 26}], "sylliah": [{"id": 63405, "mc": 220, "oc": 88}], "systematik": [{"id": 63564, "mc": 482, "oc": 82}, {"id": 182127, "mc": 4802, "oc": 196}], "sygo": [{"id": 64600, "mc": 185, "oc": 19}], "systemx": [{"id": 66311, "mc": 12, "oc": 5}], "syntho": [{"id": 67007, "mc": 8, "oc": 3}, {"id": 166733, "mc": 38, "oc": 6}], "syco": [{"id": 67374, "mc": 144, "oc": 11}, {"id": 123277, "mc": 24, "oc": 10}], "sylvano": [{"id": 69975, "mc": 37, "oc": 8}], "sy": [{"id": 71723, "mc": 13096, "oc": 155}, {"id": 99959, "mc": 1507, "oc": 94}, {"id": 153704, "mc": 1075, "oc": 263}, {"id": 162339, "mc": 89, "oc": 17}], "sylkiesmooth": [{"id": 73605, "mc": 181, "oc": 43}], "sydnie": [{"id": 74039, "mc": 131, "oc": 23}], "symbat008": [{"id": 74463, "mc": 13, "oc": 0}], "sykosiko": [{"id": 75070, "mc": 1, "oc": 0}], "sykix": [{"id": 76233, "mc": 62, "oc": 5}], "sylvinavina": [{"id": 76897, "mc": 44, "oc": 10}], "sygmei": [{"id": 77511, "mc": 84, "oc": 10}], "syno": [{"id": 78665, "mc": 105, "oc": 39}, {"id": 176894, "mc": 129, "oc": 10}], "syncmaster": [{"id": 78728, "mc": 361, "oc": 10}, {"id": 174185, "mc": 648, "oc": 51}], "synn": [{"id": 78739, "mc": 93, "oc": 30}, {"id": 142767, "mc": 868, "oc": 135}], "synstrykiir": [{"id": 78770, "mc": 521, "oc": 14}, {"id": 138864, "mc": 29, "oc": 6}], "sylenthunder": [{"id": 80337, "mc": 238, "oc": 48}], "sylvan": [{"id": 80429, "mc": 22208, "oc": 2572}], "syndicatum": [{"id": 80716, "mc": 45, "oc": 24}], "synz": [{"id": 80824, "mc": 31277, "oc": 5605}], "sychoticseagull": [{"id": 81754, "mc": 41, "oc": 4}], "synth3tk": [{"id": 81825, "mc": 14, "oc": 2}], "symin": [{"id": 84985, "mc": 128, "oc": 8}], "sychic": [{"id": 85197, "mc": 18, "oc": 4}], "syskey": [{"id": 86920, "mc": 33, "oc": 5}, {"id": 148738, "mc": 38, "oc": 5}], "synthwaveandy": [{"id": 91564, "mc": 9, "oc": 1}], "syca": [{"id": 93167, "mc": 706, "oc": 81}], "sylvia": [{"id": 94064, "mc": 164, "oc": 63}, {"id": 139817, "mc": 224, "oc": 14}], "syaz": [{"id": 95076, "mc": 153, "oc": 13}], "sylvyy": [{"id": 95331, "mc": 51, "oc": 18}], "syanide": [{"id": 95360, "mc": 75, "oc": 21}], "synnlux": [{"id": 95382, "mc": 26, "oc": 6}], "sykoxxvenomxx": [{"id": 96043, "mc": 1, "oc": 0}], "sylviaverity": [{"id": 96336, "mc": 1877, "oc": 230}], "sylvain": [{"id": 98412, "mc": 4735, "oc": 798}, {"id": 138388, "mc": 73, "oc": 18}, {"id": 157619, "mc": 47, "oc": 4}, {"id": 166540, "mc": 238, "oc": 17}], "syor": [{"id": 98784, "mc": 5, "oc": 3}], "syphinm": [{"id": 98946, "mc": 165, "oc": 64}], "syako": [{"id": 99869, "mc": 12, "oc": 4}], "sympathizer": [{"id": 100172, "mc": 16, "oc": 8}], "sylviedew": [{"id": 103695, "mc": 4, "oc": 2}], "symmetric": [{"id": 104162, "mc": 139, "oc": 20}], "sylvee": [{"id": 104401, "mc": 12370, "oc": 503}], "sykyu": [{"id": 104452, "mc": 13, "oc": 6}], "syedmuhammad": [{"id": 104856, "mc": 3325, "oc": 617}], "syrinx": [{"id": 106386, "mc": 5540, "oc": 147}], "synea": [{"id": 106634, "mc": 30, "oc": 11}], "syniuk": [{"id": 108404, "mc": 7, "oc": 0}], "syxtem": [{"id": 109294, "mc": 5, "oc": 1}], "syddy": [{"id": 109565, "mc": 45, "oc": 4}], "sylvanu": [{"id": 110369, "mc": 3399, "oc": 124}], "sypher": [{"id": 111134, "mc": 181, "oc": 48}], "sydswipe": [{"id": 111691, "mc": 49, "oc": 4}], "syon": [{"id": 112290, "mc": 1, "oc": 0}, {"id": 182598, "mc": 12, "oc": 4}], "sylan": [{"id": 112305, "mc": 96, "oc": 41}, {"id": 186015, "mc": 71, "oc": 35}], "syrrex": [{"id": 112312, "mc": 76, "oc": 13}], "synix": [{"id": 113093, "mc": 837, "oc": 195}], "sydneystar": [{"id": 116413, "mc": 12, "oc": 2}], "symbol": [{"id": 117472, "mc": 183, "oc": 10}, {"id": 134829, "mc": 555, "oc": 70}, {"id": 136005, "mc": 141, "oc": 15}], "synco": [{"id": 117622, "mc": 6, "oc": 0}], "syncthra": [{"id": 117997, "mc": 199, "oc": 39}], "synyster": [{"id": 118892, "mc": 478, "oc": 95}], "syachisan": [{"id": 120719, "mc": 56, "oc": 15}], "sydlexic": [{"id": 121186, "mc": 5, "oc": 0}], "syra": [{"id": 121726, "mc": 350, "oc": 167}], "syrenne": [{"id": 122706, "mc": 931, "oc": 216}], "syiler": [{"id": 122997, "mc": 1059, "oc": 250}], "sylver": [{"id": 123681, "mc": 244, "oc": 57}, {"id": 165166, "mc": 31, "oc": 4}, {"id": 174294, "mc": 715, "oc": 133}, {"id": 194187, "mc": 602, "oc": 37}], "syyko": [{"id": 126383, "mc": 1614, "oc": 114}], "sysadminava": [{"id": 126587, "mc": 107, "oc": 13}], "sylvertax": [{"id": 127091, "mc": 24, "oc": 4}], "sydrieth": [{"id": 128295, "mc": 1143, "oc": 110}], "symonyi": [{"id": 128979, "mc": 60, "oc": 13}], "syurin": [{"id": 132187, "mc": 53, "oc": 23}], "syben": [{"id": 132489, "mc": 23, "oc": 6}], "syfuxx": [{"id": 132605, "mc": 403, "oc": 129}], "synapstore": [{"id": 133016, "mc": 174, "oc": 27}], "syrup": [{"id": 135244, "mc": 5003, "oc": 1371}, {"id": 147212, "mc": 158, "oc": 46}], "sym": [{"id": 135890, "mc": 9, "oc": 1}], "sylve": [{"id": 136016, "mc": 28, "oc": 11}], "syousa": [{"id": 136711, "mc": 1407, "oc": 382}], "syiro": [{"id": 137807, "mc": 17, "oc": 6}, {"id": 190779, "mc": 49, "oc": 12}], "synta": [{"id": 141229, "mc": 57, "oc": 22}], "syvo": [{"id": 141248, "mc": 1731, "oc": 186}], "syborg": [{"id": 141377, "mc": 2871, "oc": 113}], "symedia": [{"id": 141528, "mc": 70, "oc": 18}], "symphonicresonance": [{"id": 142968, "mc": 160, "oc": 29}], "sylru": [{"id": 143725, "mc": 7, "oc": 1}], "system32": [{"id": 148186, "mc": 1662, "oc": 243}], "sychovorlick": [{"id": 148571, "mc": 693, "oc": 113}], "sylcent": [{"id": 148710, "mc": 26, "oc": 7}], "synnistar": [{"id": 149332, "mc": 99, "oc": 32}], "syrano": [{"id": 149557, "mc": 248, "oc": 22}], "syrine": [{"id": 150459, "mc": 22, "oc": 6}], "sylvester": [{"id": 150513, "mc": 10, "oc": 7}], "synchronenft": [{"id": 151447, "mc": 64, "oc": 7}], "syntonikka": [{"id": 151676, "mc": 276, "oc": 26}], "sycamore": [{"id": 151953, "mc": 21, "oc": 6}], "sylvain9136": [{"id": 152276, "mc": 2, "oc": 0}], "sylance": [{"id": 152441, "mc": 257, "oc": 58}], "symmetra": [{"id": 153903, "mc": 9850, "oc": 1111}], "sysel": [{"id": 154355, "mc": 11499, "oc": 89}], "syrrith": [{"id": 154392, "mc": 106, "oc": 14}], "sync667": [{"id": 154547, "mc": 196, "oc": 13}], "syliante": [{"id": 155298, "mc": 61, "oc": 8}], "syp4ik": [{"id": 156523, "mc": 99, "oc": 10}], "syunki": [{"id": 157273, "mc": 210, "oc": 12}], "syed": [{"id": 157439, "mc": 409, "oc": 20}], "synctone": [{"id": 158005, "mc": 3, "oc": 0}], "syth1k": [{"id": 158535, "mc": 40, "oc": 2}], "sydastry": [{"id": 159153, "mc": 81, "oc": 14}], "syber": [{"id": 159176, "mc": 1780, "oc": 71}], "sykke": [{"id": 160806, "mc": 39, "oc": 6}], "synia": [{"id": 162546, "mc": 3764, "oc": 1290}], "syou": [{"id": 162875, "mc": 198, "oc": 14}], "sylu": [{"id": 165048, "mc": 251, "oc": 32}], "symbiote": [{"id": 167044, "mc": 24, "oc": 6}], "syarif": [{"id": 167236, "mc": 21933, "oc": 17}], "syphorce": [{"id": 167930, "mc": 62, "oc": 15}], "symblmyne": [{"id": 168176, "mc": 3, "oc": 1}], "syml": [{"id": 168506, "mc": 428, "oc": 14}], "sybellaadmeta": [{"id": 169543, "mc": 29, "oc": 6}], "sychicboy": [{"id": 170043, "mc": 495, "oc": 38}], "syko": [{"id": 171213, "mc": 42, "oc": 12}], "sympul": [{"id": 175463, "mc": 174, "oc": 44}], "sye": [{"id": 175799, "mc": 5055, "oc": 162}], "sydew": [{"id": 181708, "mc": 587, "oc": 92}], "sylz": [{"id": 182539, "mc": 579, "oc": 16}], "sydist": [{"id": 182670, "mc": 1029, "oc": 117}], "sybeez": [{"id": 184109, "mc": 64, "oc": 17}], "syke": [{"id": 188231, "mc": 15, "oc": 4}], "syom": [{"id": 188761, "mc": 311, "oc": 18}], "sylvaned": [{"id": 189615, "mc": 202, "oc": 49}], "sydorio": [{"id": 190362, "mc": 5, "oc": 2}], "synoon": [{"id": 190950, "mc": 26, "oc": 6}], "syllabas": [{"id": 191194, "mc": 13, "oc": 7}], "synthol": [{"id": 191876, "mc": 62, "oc": 2}], "syler": [{"id": 193417, "mc": 2, "oc": 1}], "synthnewt1984": [{"id": 193780, "mc": 47, "oc": 11}], "sykocoder": [{"id": 194299, "mc": 462, "oc": 4}], "syllian": [{"id": 196595, "mc": 18, "oc": 6}], "sytei": [{"id": 196700, "mc": 373, "oc": 39}], "syntheticgm": [{"id": 197623, "mc": 33, "oc": 9}], "syamsir": [{"id": 198113, "mc": 3008, "oc": 17}]}