{"centered": [{"id": 21, "mc": 21, "oc": 5}, {"id": 2152, "mc": 9381, "oc": 1973}, {"id": 2152, "mc": 9381, "oc": 1973}, {"id": 6007, "mc": 63, "oc": 16}, {"id": 9094, "mc": 60, "oc": 24}, {"id": 10272, "mc": 1097, "oc": 137}, {"id": 11379, "mc": 250, "oc": 82}, {"id": 11765, "mc": 8, "oc": 0}, {"id": 12793, "mc": 1110, "oc": 26}, {"id": 13168, "mc": 78379, "oc": 9412}, {"id": 15835, "mc": 490, "oc": 37}, {"id": 17724, "mc": 88604, "oc": 6452}, {"id": 17778, "mc": 87, "oc": 28}, {"id": 20096, "mc": 1367, "oc": 179}, {"id": 24106, "mc": 3504, "oc": 26}, {"id": 25366, "mc": 87, "oc": 12}, {"id": 28948, "mc": 332, "oc": 10}, {"id": 30764, "mc": 4443, "oc": 644}, {"id": 33910, "mc": 2452, "oc": 563}, {"id": 35113, "mc": 104, "oc": 23}, {"id": 36629, "mc": 3515, "oc": 1226}, {"id": 36815, "mc": 14707, "oc": 2477}, {"id": 37549, "mc": 29, "oc": 6}, {"id": 39931, "mc": 6138, "oc": 818}, {"id": 40535, "mc": 10489, "oc": 1669}, {"id": 41818, "mc": 1486, "oc": 168}, {"id": 44169, "mc": 2449, "oc": 556}, {"id": 48963, "mc": 1164, "oc": 262}, {"id": 50664, "mc": 1602, "oc": 175}, {"id": 52237, "mc": 2558, "oc": 829}, {"id": 53257, "mc": 5443, "oc": 253}, {"id": 54040, "mc": 171, "oc": 30}, {"id": 54372, "mc": 35, "oc": 14}, {"id": 54526, "mc": 1270, "oc": 325}, {"id": 56442, "mc": 592, "oc": 257}, {"id": 58153, "mc": 225, "oc": 22}, {"id": 59288, "mc": 5570, "oc": 123}, {"id": 75893, "mc": 164, "oc": 35}, {"id": 76089, "mc": 4845, "oc": 2097}, {"id": 80625, "mc": 949, "oc": 123}, {"id": 83577, "mc": 20224, "oc": 7588}, {"id": 84323, "mc": 188, "oc": 21}, {"id": 88515, "mc": 73, "oc": 13}, {"id": 96806, "mc": 1596, "oc": 162}, {"id": 98012, "mc": 1032, "oc": 93}, {"id": 99768, "mc": 1196, "oc": 140}, {"id": 100647, "mc": 21, "oc": 3}, {"id": 102005, "mc": 530, "oc": 96}, {"id": 109800, "mc": 741, "oc": 213}, {"id": 113917, "mc": 1325, "oc": 219}, {"id": 115485, "mc": 27220, "oc": 5950}, {"id": 120615, "mc": 69, "oc": 24}, {"id": 124116, "mc": 181, "oc": 35}, {"id": 124675, "mc": 1340, "oc": 106}, {"id": 128155, "mc": 620, "oc": 273}, {"id": 132006, "mc": 173, "oc": 22}, {"id": 132581, "mc": 5206, "oc": 554}, {"id": 135121, "mc": 5169, "oc": 647}, {"id": 142297, "mc": 2874, "oc": 149}, {"id": 145743, "mc": 11599, "oc": 2876}, {"id": 147180, "mc": 25575, "oc": 760}, {"id": 148394, "mc": 594, "oc": 78}, {"id": 149120, "mc": 4114, "oc": 324}, {"id": 149518, "mc": 5297, "oc": 510}, {"id": 150078, "mc": 20, "oc": 6}, {"id": 153643, "mc": 2058, "oc": 699}, {"id": 154685, "mc": 735, "oc": 91}, {"id": 154816, "mc": 377, "oc": 42}, {"id": 155549, "mc": 424, "oc": 39}, {"id": 157030, "mc": 1578, "oc": 131}, {"id": 158069, "mc": 207, "oc": 40}, {"id": 162458, "mc": 179, "oc": 40}, {"id": 163587, "mc": 1421, "oc": 149}, {"id": 163813, "mc": 4759, "oc": 830}, {"id": 164143, "mc": 1445, "oc": 99}, {"id": 167784, "mc": 2003, "oc": 208}, {"id": 168335, "mc": 37088, "oc": 3186}, {"id": 168420, "mc": 442, "oc": 57}, {"id": 169545, "mc": 262, "oc": 61}, {"id": 169754, "mc": 2942, "oc": 633}, {"id": 175779, "mc": 34, "oc": 6}, {"id": 176138, "mc": 1093, "oc": 77}, {"id": 178166, "mc": 144, "oc": 10}, {"id": 180453, "mc": 398, "oc": 67}, {"id": 181518, "mc": 47, "oc": 11}, {"id": 183456, "mc": 129, "oc": 13}, {"id": 184384, "mc": 23, "oc": 2}, {"id": 184991, "mc": 2115, "oc": 189}, {"id": 192245, "mc": 166, "oc": 47}, {"id": 193262, "mc": 23, "oc": 11}, {"id": 194090, "mc": 410, "oc": 113}, {"id": 195276, "mc": 65018, "oc": 6679}, {"id": 196160, "mc": 18, "oc": 8}, {"id": 198432, "mc": 1474, "oc": 294}, {"id": 198770, "mc": 3114, "oc": 344}, {"id": 200468, "mc": 4469, "oc": 747}, {"id": 202387, "mc": 262, "oc": 48}, {"id": 209029, "mc": 7256, "oc": 795}, {"id": 211737, "mc": 4174, "oc": 150}, {"id": 211888, "mc": 20, "oc": 5}, {"id": 214947, "mc": 46, "oc": 3}, {"id": 215752, "mc": 121, "oc": 17}, {"id": 215756, "mc": 615, "oc": 47}, {"id": 215808, "mc": 86, "oc": 29}, {"id": 216646, "mc": 172, "oc": 53}, {"id": 219060, "mc": 416, "oc": 50}, {"id": 219111, "mc": 333, "oc": 32}, {"id": 221393, "mc": 35, "oc": 5}, {"id": 221407, "mc": 11, "oc": 4}, {"id": 226141, "mc": 10508, "oc": 1558}, {"id": 226262, "mc": 169, "oc": 68}, {"id": 226310, "mc": 1317, "oc": 48}, {"id": 227459, "mc": 279, "oc": 102}, {"id": 228259, "mc": 562, "oc": 140}, {"id": 228293, "mc": 5403, "oc": 1580}, {"id": 230086, "mc": 6238, "oc": 1265}, {"id": 231816, "mc": 25, "oc": 7}, {"id": 233429, "mc": 87, "oc": 9}, {"id": 235275, "mc": 9987, "oc": 1460}, {"id": 236098, "mc": 118, "oc": 43}, {"id": 241703, "mc": 385, "oc": 90}, {"id": 243279, "mc": 48172, "oc": 3468}, {"id": 247541, "mc": 51, "oc": 14}, {"id": 248541, "mc": 11787, "oc": 1060}], "ceiling": [{"id": 174, "mc": 1045, "oc": 145}], "celebrate": [{"id": 1205, "mc": 150, "oc": 7}, {"id": 5223, "mc": 10181, "oc": 332}, {"id": 9416, "mc": 27, "oc": 9}, {"id": 10281, "mc": 58, "oc": 13}, {"id": 14201, "mc": 348, "oc": 58}, {"id": 14512, "mc": 3, "oc": 0}, {"id": 14617, "mc": 51, "oc": 14}, {"id": 15417, "mc": 2126, "oc": 260}, {"id": 17941, "mc": 1211, "oc": 201}, {"id": 32199, "mc": 841, "oc": 65}, {"id": 37016, "mc": 44033, "oc": 9649}, {"id": 55232, "mc": 311, "oc": 23}, {"id": 59272, "mc": 2282, "oc": 258}, {"id": 61587, "mc": 1849, "oc": 229}, {"id": 68133, "mc": 2975, "oc": 877}, {"id": 72590, "mc": 882, "oc": 114}, {"id": 73349, "mc": 35401, "oc": 6105}, {"id": 75508, "mc": 1250, "oc": 121}, {"id": 86118, "mc": 1101, "oc": 116}, {"id": 96736, "mc": 282, "oc": 92}, {"id": 98107, "mc": 1153, "oc": 36}, {"id": 100828, "mc": 5, "oc": 3}, {"id": 107439, "mc": 63, "oc": 6}, {"id": 113400, "mc": 145, "oc": 24}, {"id": 119474, "mc": 170, "oc": 37}, {"id": 128919, "mc": 1165, "oc": 310}, {"id": 130245, "mc": 30, "oc": 16}, {"id": 135363, "mc": 378, "oc": 121}, {"id": 135594, "mc": 385, "oc": 40}, {"id": 140408, "mc": 317, "oc": 41}, {"id": 143792, "mc": 161, "oc": 30}, {"id": 150124, "mc": 275, "oc": 79}, {"id": 156380, "mc": 39, "oc": 14}, {"id": 157658, "mc": 1541, "oc": 123}, {"id": 159256, "mc": 257, "oc": 65}, {"id": 160557, "mc": 1504, "oc": 190}, {"id": 162694, "mc": 1632, "oc": 88}, {"id": 162882, "mc": 213, "oc": 46}, {"id": 165732, "mc": 46, "oc": 4}, {"id": 167171, "mc": 1518, "oc": 220}, {"id": 174489, "mc": 1376, "oc": 115}, {"id": 175712, "mc": 123, "oc": 10}, {"id": 175897, "mc": 21, "oc": 4}, {"id": 182368, "mc": 1915, "oc": 198}, {"id": 197854, "mc": 1047, "oc": 43}, {"id": 216279, "mc": 5735, "oc": 2117}, {"id": 218939, "mc": 117, "oc": 55}, {"id": 222224, "mc": 37, "oc": 6}, {"id": 235156, "mc": 112, "oc": 20}, {"id": 238444, "mc": 3273, "oc": 238}], "cere": [{"id": 1447, "mc": 3991, "oc": 176}], "cenobium": [{"id": 2821, "mc": 378, "oc": 40}], "celestial": [{"id": 3132, "mc": 11225, "oc": 31}, {"id": 44628, "mc": 383, "oc": 141}, {"id": 55893, "mc": 5697, "oc": 1245}, {"id": 65379, "mc": 4673, "oc": 218}, {"id": 65379, "mc": 4673, "oc": 218}, {"id": 95757, "mc": 177, "oc": 41}, {"id": 101103, "mc": 156, "oc": 20}, {"id": 128287, "mc": 325, "oc": 47}, {"id": 139988, "mc": 891, "oc": 20}, {"id": 147437, "mc": 2552, "oc": 162}, {"id": 174903, "mc": 95, "oc": 29}, {"id": 198820, "mc": 1644, "oc": 261}, {"id": 216729, "mc": 965, "oc": 62}, {"id": 221804, "mc": 122, "oc": 18}, {"id": 229409, "mc": 1173, "oc": 634}], "century": [{"id": 3149, "mc": 3580, "oc": 122}, {"id": 45124, "mc": 62, "oc": 2}, {"id": 77095, "mc": 1246, "oc": 140}, {"id": 109460, "mc": 86, "oc": 18}, {"id": 137098, "mc": 245, "oc": 63}, {"id": 162153, "mc": 288, "oc": 55}, {"id": 204590, "mc": 1135, "oc": 35}, {"id": 221216, "mc": 20323, "oc": 4260}, {"id": 225539, "mc": 77, "oc": 8}, {"id": 242778, "mc": 264471, "oc": 50652}], "central": [{"id": 3688, "mc": 131, "oc": 15}, {"id": 4933, "mc": 1037, "oc": 29}, {"id": 5732, "mc": 12280, "oc": 2100}, {"id": 6964, "mc": 10, "oc": 0}, {"id": 20531, "mc": 197, "oc": 28}, {"id": 21228, "mc": 1084, "oc": 208}, {"id": 25385, "mc": 101, "oc": 30}, {"id": 26845, "mc": 89, "oc": 47}, {"id": 29157, "mc": 441, "oc": 75}, {"id": 30784, "mc": 2188, "oc": 562}, {"id": 33190, "mc": 42, "oc": 4}, {"id": 34782, "mc": 14650, "oc": 1987}, {"id": 35566, "mc": 86287, "oc": 2748}, {"id": 37088, "mc": 27683, "oc": 3747}, {"id": 40605, "mc": 7, "oc": 1}, {"id": 43602, "mc": 93, "oc": 7}, {"id": 47103, "mc": 32, "oc": 3}, {"id": 51402, "mc": 19674, "oc": 5650}, {"id": 53341, "mc": 1139, "oc": 276}, {"id": 53471, "mc": 943, "oc": 251}, {"id": 55111, "mc": 2280, "oc": 322}, {"id": 56710, "mc": 12853, "oc": 2805}, {"id": 57913, "mc": 73, "oc": 20}, {"id": 58622, "mc": 37, "oc": 9}, {"id": 58703, "mc": 13105, "oc": 904}, {"id": 59220, "mc": 47, "oc": 13}, {"id": 59288, "mc": 5570, "oc": 123}, {"id": 59406, "mc": 2552, "oc": 125}, {"id": 59894, "mc": 12, "oc": 1}, {"id": 60508, "mc": 57496, "oc": 9835}, {"id": 77051, "mc": 2719, "oc": 136}, {"id": 77140, "mc": 732, "oc": 158}, {"id": 80841, "mc": 5, "oc": 2}, {"id": 81518, "mc": 592, "oc": 138}, {"id": 84987, "mc": 75, "oc": 2}, {"id": 87521, "mc": 2926, "oc": 525}, {"id": 93107, "mc": 4221, "oc": 982}, {"id": 94407, "mc": 1342, "oc": 233}, {"id": 105449, "mc": 18842, "oc": 1975}, {"id": 111339, "mc": 41, "oc": 2}, {"id": 113040, "mc": 1638, "oc": 264}, {"id": 114235, "mc": 814, "oc": 59}, {"id": 114612, "mc": 1847, "oc": 274}, {"id": 114971, "mc": 6867, "oc": 183}, {"id": 119637, "mc": 2193, "oc": 1011}, {"id": 119844, "mc": 61, "oc": 19}, {"id": 125299, "mc": 345, "oc": 79}, {"id": 125299, "mc": 345, "oc": 79}, {"id": 130978, "mc": 1528, "oc": 36}, {"id": 135980, "mc": 7166, "oc": 1496}, {"id": 139868, "mc": 97, "oc": 45}, {"id": 145893, "mc": 1256, "oc": 151}, {"id": 153048, "mc": 26392, "oc": 3842}, {"id": 155308, "mc": 2900, "oc": 236}, {"id": 156912, "mc": 455, "oc": 128}, {"id": 159187, "mc": 5793, "oc": 1290}, {"id": 160158, "mc": 441, "oc": 42}, {"id": 163278, "mc": 325, "oc": 19}, {"id": 163692, "mc": 452, "oc": 74}, {"id": 164605, "mc": 13497, "oc": 4035}, {"id": 168870, "mc": 766, "oc": 196}, {"id": 173670, "mc": 2141, "oc": 375}, {"id": 173703, "mc": 3688, "oc": 749}, {"id": 174737, "mc": 137, "oc": 19}, {"id": 175904, "mc": 1271, "oc": 32}, {"id": 177094, "mc": 169, "oc": 22}, {"id": 179813, "mc": 6146, "oc": 323}, {"id": 189673, "mc": 2694, "oc": 110}, {"id": 190967, "mc": 712, "oc": 155}, {"id": 195255, "mc": 49, "oc": 10}, {"id": 195255, "mc": 49, "oc": 10}, {"id": 201656, "mc": 3972, "oc": 958}, {"id": 203154, "mc": 586, "oc": 124}, {"id": 207201, "mc": 1478, "oc": 195}, {"id": 210324, "mc": 706, "oc": 187}, {"id": 213386, "mc": 1444, "oc": 80}, {"id": 216031, "mc": 272, "oc": 51}, {"id": 218302, "mc": 106, "oc": 16}, {"id": 222489, "mc": 6767, "oc": 1034}, {"id": 226286, "mc": 2542, "oc": 323}, {"id": 228063, "mc": 240, "oc": 48}, {"id": 234004, "mc": 441, "oc": 63}, {"id": 235425, "mc": 85, "oc": 35}, {"id": 243250, "mc": 87, "oc": 19}, {"id": 244589, "mc": 161, "oc": 46}, {"id": 246071, "mc": 10929, "oc": 1502}, {"id": 247283, "mc": 61, "oc": 20}, {"id": 248288, "mc": 734, "oc": 169}, {"id": 248426, "mc": 650, "oc": 64}, {"id": 249828, "mc": 42, "oc": 22}], "centralfiction": [{"id": 4178, "mc": 18904, "oc": 6186}], "certo": [{"id": 4197, "mc": 750, "oc": 82}, {"id": 66011, "mc": 5148, "oc": 698}, {"id": 66712, "mc": 3044, "oc": 35}, {"id": 92139, "mc": 1233, "oc": 24}, {"id": 108006, "mc": 6647, "oc": 747}, {"id": 161671, "mc": 2757, "oc": 108}, {"id": 177990, "mc": 24291, "oc": 1551}, {"id": 179487, "mc": 10691, "oc": 3220}, {"id": 185735, "mc": 85, "oc": 5}, {"id": 234639, "mc": 861, "oc": 120}, {"id": 236892, "mc": 518, "oc": 74}], "centro": [{"id": 4402, "mc": 1925, "oc": 41}, {"id": 10653, "mc": 323, "oc": 114}, {"id": 52597, "mc": 2367, "oc": 201}, {"id": 74822, "mc": 1784, "oc": 6}, {"id": 80081, "mc": 2393, "oc": 215}, {"id": 103616, "mc": 78, "oc": 13}, {"id": 148568, "mc": 3175, "oc": 509}, {"id": 227417, "mc": 66, "oc": 11}], "center": [{"id": 4477, "mc": 5927, "oc": 145}, {"id": 29062, "mc": 860, "oc": 138}, {"id": 35471, "mc": 70, "oc": 17}, {"id": 37716, "mc": 104, "oc": 9}, {"id": 41732, "mc": 2688, "oc": 114}, {"id": 43022, "mc": 6996, "oc": 1800}, {"id": 47298, "mc": 226, "oc": 35}, {"id": 49781, "mc": 54984, "oc": 9009}, {"id": 59666, "mc": 1199, "oc": 169}, {"id": 59666, "mc": 1199, "oc": 169}, {"id": 64872, "mc": 2647, "oc": 721}, {"id": 65953, "mc": 2853, "oc": 522}, {"id": 69709, "mc": 38, "oc": 8}, {"id": 88749, "mc": 13675, "oc": 100}, {"id": 91182, "mc": 74, "oc": 27}, {"id": 91866, "mc": 4376, "oc": 76}, {"id": 92511, "mc": 264, "oc": 61}, {"id": 93776, "mc": 137648, "oc": 16518}, {"id": 93908, "mc": 100, "oc": 26}, {"id": 98979, "mc": 41, "oc": 18}, {"id": 100145, "mc": 18898, "oc": 5687}, {"id": 101608, "mc": 50, "oc": 12}, {"id": 106835, "mc": 1910, "oc": 334}, {"id": 109898, "mc": 37069, "oc": 9278}, {"id": 116445, "mc": 54697, "oc": 19804}, {"id": 121059, "mc": 1084, "oc": 347}, {"id": 126400, "mc": 3330, "oc": 1242}, {"id": 137741, "mc": 1516, "oc": 352}, {"id": 139588, "mc": 80, "oc": 15}, {"id": 143812, "mc": 4770, "oc": 861}, {"id": 149459, "mc": 1455434, "oc": 46498}, {"id": 150596, "mc": 531, "oc": 26}, {"id": 150848, "mc": 91, "oc": 37}, {"id": 156287, "mc": 2314, "oc": 555}, {"id": 156287, "mc": 2314, "oc": 555}, {"id": 166990, "mc": 90, "oc": 20}, {"id": 167194, "mc": 8538, "oc": 69}, {"id": 168183, "mc": 2384, "oc": 178}, {"id": 169008, "mc": 8849, "oc": 338}, {"id": 170949, "mc": 502, "oc": 52}, {"id": 171933, "mc": 1431, "oc": 249}, {"id": 176005, "mc": 69, "oc": 20}, {"id": 180600, "mc": 118, "oc": 24}, {"id": 186318, "mc": 4516, "oc": 751}, {"id": 192403, "mc": 99, "oc": 31}, {"id": 193357, "mc": 1502, "oc": 108}, {"id": 205308, "mc": 13430, "oc": 648}, {"id": 213569, "mc": 5421, "oc": 2516}, {"id": 213581, "mc": 1678, "oc": 118}, {"id": 217707, "mc": 535, "oc": 25}, {"id": 224290, "mc": 1077, "oc": 80}, {"id": 225026, "mc": 314, "oc": 51}, {"id": 235561, "mc": 176, "oc": 22}, {"id": 240306, "mc": 463, "oc": 107}, {"id": 247104, "mc": 237, "oc": 110}, {"id": 247394, "mc": 84, "oc": 29}, {"id": 248116, "mc": 81, "oc": 17}], "cercano": [{"id": 5034, "mc": 584, "oc": 18}, {"id": 184511, "mc": 229, "oc": 27}], "certified": [{"id": 5451, "mc": 1357, "oc": 39}, {"id": 32883, "mc": 6269, "oc": 250}, {"id": 119286, "mc": 119, "oc": 23}, {"id": 122700, "mc": 1086, "oc": 122}, {"id": 143510, "mc": 184, "oc": 46}, {"id": 185587, "mc": 1494, "oc": 230}, {"id": 214412, "mc": 47, "oc": 15}], "centric": [{"id": 7523, "mc": 983, "oc": 60}, {"id": 8492, "mc": 535, "oc": 89}, {"id": 12756, "mc": 26631, "oc": 3218}, {"id": 22751, "mc": 274449, "oc": 3188}, {"id": 24169, "mc": 348, "oc": 160}, {"id": 28611, "mc": 279, "oc": 94}, {"id": 36107, "mc": 17922, "oc": 730}, {"id": 37042, "mc": 11567, "oc": 109}, {"id": 43962, "mc": 11473, "oc": 534}, {"id": 53194, "mc": 695, "oc": 297}, {"id": 73994, "mc": 15056, "oc": 3946}, {"id": 75509, "mc": 6271, "oc": 870}, {"id": 112721, "mc": 457, "oc": 60}, {"id": 121045, "mc": 4784, "oc": 54}, {"id": 122606, "mc": 265, "oc": 136}, {"id": 135167, "mc": 471, "oc": 31}, {"id": 135656, "mc": 309, "oc": 42}, {"id": 165533, "mc": 656, "oc": 82}, {"id": 201937, "mc": 271, "oc": 57}, {"id": 206858, "mc": 233, "oc": 43}, {"id": 215556, "mc": 1406, "oc": 101}, {"id": 220977, "mc": 35047, "oc": 10102}, {"id": 231275, "mc": 83, "oc": 20}, {"id": 244621, "mc": 11, "oc": 5}], "ce": [{"id": 7849, "mc": 156, "oc": 7}, {"id": 8814, "mc": 42228, "oc": 3559}, {"id": 14476, "mc": 4280, "oc": 961}, {"id": 15345, "mc": 17, "oc": 4}, {"id": 15674, "mc": 16, "oc": 4}, {"id": 15674, "mc": 16, "oc": 4}, {"id": 24509, "mc": 90, "oc": 4}, {"id": 26623, "mc": 136, "oc": 31}, {"id": 26623, "mc": 136, "oc": 31}, {"id": 28376, "mc": 109, "oc": 7}, {"id": 29776, "mc": 13, "oc": 7}, {"id": 37463, "mc": 9, "oc": 3}, {"id": 37692, "mc": 2325, "oc": 194}, {"id": 41186, "mc": 38, "oc": 8}, {"id": 52309, "mc": 638, "oc": 29}, {"id": 57423, "mc": 45, "oc": 11}, {"id": 58839, "mc": 7708, "oc": 1173}, {"id": 61550, "mc": 3153, "oc": 134}, {"id": 63308, "mc": 334, "oc": 45}, {"id": 69704, "mc": 19042, "oc": 381}, {"id": 72847, "mc": 40, "oc": 7}, {"id": 73869, "mc": 3086, "oc": 73}, {"id": 83403, "mc": 49, "oc": 5}, {"id": 83403, "mc": 49, "oc": 5}, {"id": 86207, "mc": 541, "oc": 11}, {"id": 89469, "mc": 9765, "oc": 1075}, {"id": 90676, "mc": 4100, "oc": 228}, {"id": 91660, "mc": 26, "oc": 8}, {"id": 93523, "mc": 646, "oc": 21}, {"id": 94201, "mc": 3326, "oc": 370}, {"id": 94345, "mc": 444, "oc": 22}, {"id": 99745, "mc": 4523, "oc": 270}, {"id": 100267, "mc": 34, "oc": 14}, {"id": 100900, "mc": 343, "oc": 20}, {"id": 107125, "mc": 102, "oc": 23}, {"id": 107755, "mc": 328, "oc": 38}, {"id": 111581, "mc": 28, "oc": 2}, {"id": 113544, "mc": 6996, "oc": 1255}, {"id": 115113, "mc": 132, "oc": 41}, {"id": 115210, "mc": 135, "oc": 47}, {"id": 126847, "mc": 1463, "oc": 107}, {"id": 128476, "mc": 155, "oc": 42}, {"id": 129384, "mc": 6894, "oc": 2388}, {"id": 129473, "mc": 150, "oc": 44}, {"id": 131167, "mc": 1160, "oc": 44}, {"id": 131889, "mc": 14, "oc": 5}, {"id": 133988, "mc": 2108, "oc": 315}, {"id": 134030, "mc": 853, "oc": 168}, {"id": 134469, "mc": 1869, "oc": 82}, {"id": 136560, "mc": 27, "oc": 14}, {"id": 153006, "mc": 32, "oc": 6}, {"id": 154038, "mc": 9874, "oc": 542}, {"id": 156568, "mc": 25, "oc": 8}, {"id": 161969, "mc": 136, "oc": 28}, {"id": 162696, "mc": 32, "oc": 5}, {"id": 165521, "mc": 45793, "oc": 4158}, {"id": 165978, "mc": 39, "oc": 3}, {"id": 166854, "mc": 36, "oc": 1}, {"id": 168219, "mc": 45534, "oc": 9800}, {"id": 168826, "mc": 140, "oc": 24}, {"id": 171193, "mc": 135, "oc": 15}, {"id": 171663, "mc": 8356, "oc": 2671}, {"id": 171663, "mc": 8356, "oc": 2671}, {"id": 171663, "mc": 8356, "oc": 2671}, {"id": 175347, "mc": 16, "oc": 5}, {"id": 176717, "mc": 37, "oc": 16}, {"id": 178099, "mc": 40, "oc": 12}, {"id": 178575, "mc": 675, "oc": 132}, {"id": 180231, "mc": 307, "oc": 40}, {"id": 181919, "mc": 3384, "oc": 360}, {"id": 184668, "mc": 1918, "oc": 282}, {"id": 188670, "mc": 851, "oc": 106}, {"id": 192799, "mc": 2150, "oc": 380}, {"id": 194398, "mc": 110, "oc": 24}, {"id": 199325, "mc": 229, "oc": 72}, {"id": 201083, "mc": 12815, "oc": 852}, {"id": 204946, "mc": 668, "oc": 75}, {"id": 206500, "mc": 405, "oc": 48}, {"id": 208870, "mc": 227, "oc": 51}, {"id": 210139, "mc": 29, "oc": 10}, {"id": 214367, "mc": 176, "oc": 34}, {"id": 215856, "mc": 120, "oc": 27}, {"id": 220271, "mc": 518, "oc": 71}, {"id": 220316, "mc": 263, "oc": 97}, {"id": 223472, "mc": 1072, "oc": 250}, {"id": 223582, "mc": 114, "oc": 11}, {"id": 225055, "mc": 2444, "oc": 422}, {"id": 227825, "mc": 335, "oc": 34}, {"id": 228184, "mc": 4595, "oc": 707}, {"id": 232132, "mc": 21, "oc": 0}, {"id": 232533, "mc": 48, "oc": 7}, {"id": 233057, "mc": 829, "oc": 71}, {"id": 234390, "mc": 85, "oc": 24}, {"id": 237805, "mc": 293, "oc": 66}, {"id": 239496, "mc": 148, "oc": 32}, {"id": 247684, "mc": 775, "oc": 63}], "celestia": [{"id": 8415, "mc": 17, "oc": 4}, {"id": 19839, "mc": 4599, "oc": 373}, {"id": 32625, "mc": 7931, "oc": 347}, {"id": 40334, "mc": 22250, "oc": 1571}], "cet": [{"id": 8488, "mc": 1196, "oc": 104}, {"id": 41638, "mc": 202, "oc": 18}, {"id": 57974, "mc": 371, "oc": 129}, {"id": 170218, "mc": 378, "oc": 49}, {"id": 223802, "mc": 2593, "oc": 111}, {"id": 223802, "mc": 2593, "oc": 111}], "cercare": [{"id": 8707, "mc": 14417, "oc": 981}], "cell": [{"id": 8738, "mc": 495, "oc": 184}, {"id": 56430, "mc": 5563, "oc": 70}, {"id": 56430, "mc": 5563, "oc": 70}, {"id": 71692, "mc": 858, "oc": 36}, {"id": 97307, "mc": 8171, "oc": 812}, {"id": 153742, "mc": 10525, "oc": 3543}, {"id": 158433, "mc": 33640, "oc": 8038}, {"id": 236424, "mc": 44, "oc": 6}], "centennial": [{"id": 8775, "mc": 61, "oc": 20}], "cedh": [{"id": 9246, "mc": 1987, "oc": 361}, {"id": 14708, "mc": 4909, "oc": 1189}, {"id": 24478, "mc": 1509, "oc": 233}, {"id": 54671, "mc": 1164, "oc": 227}, {"id": 76954, "mc": 662, "oc": 108}, {"id": 76954, "mc": 662, "oc": 108}, {"id": 216020, "mc": 1696, "oc": 303}], "centre": [{"id": 11960, "mc": 29457, "oc": 2452}, {"id": 29351, "mc": 1737, "oc": 116}, {"id": 33958, "mc": 498, "oc": 65}, {"id": 38268, "mc": 1291, "oc": 129}, {"id": 53104, "mc": 122, "oc": 35}, {"id": 115699, "mc": 41233, "oc": 5768}, {"id": 127622, "mc": 1508, "oc": 130}, {"id": 142094, "mc": 3307, "oc": 317}, {"id": 172006, "mc": 149, "oc": 21}, {"id": 179813, "mc": 6146, "oc": 323}, {"id": 195567, "mc": 728, "oc": 70}, {"id": 215239, "mc": 6, "oc": 0}, {"id": 217636, "mc": 47, "oc": 11}, {"id": 228374, "mc": 6123, "oc": 388}], "centauri": [{"id": 12132, "mc": 2658, "oc": 620}, {"id": 45658, "mc": 4219, "oc": 30}, {"id": 209989, "mc": 96, "oc": 5}], "cea": [{"id": 12137, "mc": 11737, "oc": 1052}, {"id": 99359, "mc": 2399, "oc": 181}, {"id": 138756, "mc": 1196, "oc": 164}], "celio": [{"id": 12401, "mc": 809, "oc": 116}], "celu": [{"id": 13522, "mc": 306, "oc": 44}, {"id": 96023, "mc": 50, "oc": 8}, {"id": 133184, "mc": 47, "oc": 15}], "celebrating": [{"id": 13544, "mc": 83, "oc": 1}, {"id": 15226, "mc": 1412, "oc": 401}, {"id": 45094, "mc": 5009, "oc": 562}, {"id": 51099, "mc": 179, "oc": 13}, {"id": 52631, "mc": 763, "oc": 141}, {"id": 53987, "mc": 1362, "oc": 198}, {"id": 66606, "mc": 6447, "oc": 1299}, {"id": 73704, "mc": 130, "oc": 41}, {"id": 81476, "mc": 2627, "oc": 165}, {"id": 82497, "mc": 197, "oc": 22}, {"id": 109816, "mc": 5274, "oc": 914}, {"id": 111484, "mc": 1486, "oc": 317}, {"id": 115881, "mc": 2444, "oc": 366}, {"id": 116254, "mc": 631, "oc": 68}, {"id": 128249, "mc": 623, "oc": 248}, {"id": 145090, "mc": 98, "oc": 19}, {"id": 159173, "mc": 51, "oc": 12}, {"id": 159257, "mc": 26, "oc": 6}, {"id": 166306, "mc": 64324, "oc": 375}, {"id": 172140, "mc": 1768, "oc": 162}, {"id": 186493, "mc": 972, "oc": 129}, {"id": 208896, "mc": 960, "oc": 9}, {"id": 213127, "mc": 6452, "oc": 754}, {"id": 235408, "mc": 250, "oc": 42}, {"id": 247283, "mc": 61, "oc": 20}, {"id": 248154, "mc": 1383, "oc": 404}], "cellular": [{"id": 14241, "mc": 1838, "oc": 253}], "centramo": [{"id": 15781, "mc": 32, "oc": 18}, {"id": 86266, "mc": 1206, "oc": 31}, {"id": 163872, "mc": 10696, "oc": 110}], "cerrado": [{"id": 16049, "mc": 40, "oc": 19}], "ceo": [{"id": 16221, "mc": 8282, "oc": 113}, {"id": 64990, "mc": 667, "oc": 67}, {"id": 65895, "mc": 8034, "oc": 674}, {"id": 176315, "mc": 26291, "oc": 597}, {"id": 214074, "mc": 243, "oc": 38}], "celebritie": [{"id": 17370, "mc": 2399, "oc": 62}, {"id": 46946, "mc": 211, "oc": 10}, {"id": 118417, "mc": 2826, "oc": 41}, {"id": 209109, "mc": 4637, "oc": 22}], "centralized": [{"id": 17476, "mc": 2824, "oc": 99}, {"id": 23844, "mc": 146382, "oc": 12180}, {"id": 31487, "mc": 33685, "oc": 12711}, {"id": 36265, "mc": 14011, "oc": 16}, {"id": 38056, "mc": 1292, "oc": 170}, {"id": 128632, "mc": 18502, "oc": 768}, {"id": 198026, "mc": 81, "oc": 24}], "centrado": [{"id": 18495, "mc": 2027, "oc": 360}, {"id": 34686, "mc": 112, "oc": 16}, {"id": 34686, "mc": 112, "oc": 16}, {"id": 85765, "mc": 2054, "oc": 234}, {"id": 191311, "mc": 2260, "oc": 309}, {"id": 244635, "mc": 2292, "oc": 25}, {"id": 244995, "mc": 205, "oc": 17}], "celuvplay": [{"id": 19120, "mc": 39180, "oc": 155}], "centred": [{"id": 19391, "mc": 157, "oc": 12}, {"id": 70027, "mc": 866, "oc": 75}, {"id": 83142, "mc": 9, "oc": 8}, {"id": 95282, "mc": 32, "oc": 7}, {"id": 103725, "mc": 17520, "oc": 2521}, {"id": 106987, "mc": 72, "oc": 18}, {"id": 111910, "mc": 18879, "oc": 4312}, {"id": 144138, "mc": 217, "oc": 10}, {"id": 164698, "mc": 126, "oc": 32}, {"id": 223010, "mc": 272, "oc": 68}, {"id": 247952, "mc": 2767, "oc": 797}], "cellofrag": [{"id": 19757, "mc": 17007, "oc": 2569}], "centuria": [{"id": 20542, "mc": 16258, "oc": 195}], "celeste": [{"id": 23447, "mc": 79, "oc": 23}, {"id": 23512, "mc": 83540, "oc": 19924}, {"id": 63829, "mc": 2049, "oc": 621}, {"id": 63829, "mc": 2049, "oc": 621}, {"id": 154510, "mc": 51, "oc": 15}], "celina": [{"id": 23961, "mc": 1204, "oc": 274}, {"id": 23961, "mc": 1204, "oc": 274}], "ceea": [{"id": 24509, "mc": 90, "oc": 4}], "cement": [{"id": 28775, "mc": 4, "oc": 2}], "ceux": [{"id": 29238, "mc": 3365, "oc": 202}, {"id": 80867, "mc": 42, "oc": 4}, {"id": 112392, "mc": 578, "oc": 154}, {"id": 116274, "mc": 39, "oc": 18}, {"id": 128476, "mc": 155, "oc": 42}, {"id": 144254, "mc": 7, "oc": 2}, {"id": 172410, "mc": 1087, "oc": 43}, {"id": 187833, "mc": 16, "oc": 4}, {"id": 199027, "mc": 194, "oc": 81}, {"id": 216582, "mc": 316, "oc": 54}, {"id": 232841, "mc": 202, "oc": 41}], "cecilia": [{"id": 29469, "mc": 4007, "oc": 1765}, {"id": 29469, "mc": 4007, "oc": 1765}], "cemetery": [{"id": 29646, "mc": 29, "oc": 14}, {"id": 53438, "mc": 8398, "oc": 2212}], "cenario": [{"id": 31745, "mc": 17, "oc": 3}], "certification": [{"id": 31934, "mc": 28889, "oc": 1785}, {"id": 64170, "mc": 1390, "oc": 143}, {"id": 113181, "mc": 168, "oc": 13}, {"id": 185454, "mc": 30691, "oc": 3081}, {"id": 205144, "mc": 7639, "oc": 71}, {"id": 221024, "mc": 7233, "oc": 805}, {"id": 247141, "mc": 26038, "oc": 3080}], "certain": [{"id": 32241, "mc": 190, "oc": 18}, {"id": 93674, "mc": 2803, "oc": 146}, {"id": 108403, "mc": 1691, "oc": 223}, {"id": 132958, "mc": 33, "oc": 4}, {"id": 140146, "mc": 36, "oc": 16}, {"id": 165466, "mc": 657, "oc": 38}], "cerbralpalsy": [{"id": 33293, "mc": 2387, "oc": 134}], "cerebral": [{"id": 33293, "mc": 2387, "oc": 134}], "centrifuge": [{"id": 33874, "mc": 18035, "oc": 688}], "censorship": [{"id": 34079, "mc": 626, "oc": 53}, {"id": 63273, "mc": 2068, "oc": 187}, {"id": 110270, "mc": 24, "oc": 1}, {"id": 114438, "mc": 545, "oc": 106}, {"id": 120472, "mc": 84, "oc": 24}], "celou": [{"id": 37579, "mc": 2038, "oc": 225}], "centering": [{"id": 38275, "mc": 133, "oc": 33}, {"id": 192230, "mc": 13360, "oc": 1056}], "centurie": [{"id": 38467, "mc": 358, "oc": 84}], "celtic": [{"id": 38646, "mc": 4628, "oc": 762}, {"id": 99734, "mc": 5470, "oc": 362}, {"id": 99734, "mc": 5470, "oc": 362}, {"id": 99734, "mc": 5470, "oc": 362}], "cesarfever": [{"id": 39931, "mc": 6138, "oc": 818}], "celle": [{"id": 40692, "mc": 962, "oc": 51}, {"id": 116274, "mc": 39, "oc": 18}, {"id": 123968, "mc": 759, "oc": 113}, {"id": 127412, "mc": 322, "oc": 34}], "cerbermint": [{"id": 45600, "mc": 8791, "oc": 507}], "celeb": [{"id": 46004, "mc": 92594, "oc": 3306}], "celui": [{"id": 47645, "mc": 496, "oc": 98}, {"id": 171193, "mc": 135, "oc": 15}, {"id": 181919, "mc": 3384, "oc": 360}, {"id": 247684, "mc": 775, "oc": 63}], "cex": [{"id": 48040, "mc": 18666, "oc": 909}, {"id": 55727, "mc": 2308, "oc": 106}, {"id": 100787, "mc": 6314, "oc": 16}, {"id": 229667, "mc": 1897, "oc": 171}, {"id": 236626, "mc": 194, "oc": 9}], "celophy": [{"id": 49302, "mc": 1676, "oc": 227}], "centurion": [{"id": 49390, "mc": 20, "oc": 10}], "cefi": [{"id": 50456, "mc": 67960, "oc": 2153}, {"id": 62051, "mc": 4450, "oc": 246}, {"id": 94109, "mc": 4689, "oc": 20}, {"id": 110649, "mc": 2550, "oc": 9}, {"id": 129814, "mc": 28773, "oc": 380}, {"id": 157727, "mc": 694, "oc": 24}], "celleux": [{"id": 51980, "mc": 53, "oc": 8}], "centra": [{"id": 52365, "mc": 87, "oc": 6}], "cenza": [{"id": 54932, "mc": 1761, "oc": 72}], "celem": [{"id": 55333, "mc": 3717, "oc": 44}], "celebrity": [{"id": 55526, "mc": 22752, "oc": 299}, {"id": 67557, "mc": 8032, "oc": 613}, {"id": 106952, "mc": 7726, "oc": 1359}, {"id": 150913, "mc": 4, "oc": 0}, {"id": 173077, "mc": 18155, "oc": 21}], "ceci": [{"id": 55970, "mc": 151, "oc": 23}, {"id": 153540, "mc": 52, "oc": 9}, {"id": 158636, "mc": 52, "oc": 11}, {"id": 166016, "mc": 53, "oc": 12}], "cependant": [{"id": 61430, "mc": 29, "oc": 7}], "cereno": [{"id": 63785, "mc": 4667, "oc": 287}], "centrada": [{"id": 67943, "mc": 803, "oc": 61}, {"id": 79885, "mc": 21439, "oc": 1040}, {"id": 98339, "mc": 1351, "oc": 210}, {"id": 134429, "mc": 89, "oc": 13}, {"id": 173576, "mc": 798, "oc": 49}, {"id": 198942, "mc": 10765, "oc": 186}], "ces": [{"id": 69694, "mc": 22205, "oc": 7792}, {"id": 129969, "mc": 255419, "oc": 3962}, {"id": 187722, "mc": 131, "oc": 23}], "cetera": [{"id": 72023, "mc": 8, "oc": 4}], "cerber": [{"id": 73491, "mc": 112, "oc": 9}], "centralization": [{"id": 75669, "mc": 411, "oc": 28}], "cerealcraft": [{"id": 76912, "mc": 628, "oc": 30}], "cette": [{"id": 78156, "mc": 1250, "oc": 46}, {"id": 234390, "mc": 85, "oc": 24}, {"id": 244446, "mc": 86, "oc": 35}], "centralised": [{"id": 78176, "mc": 568, "oc": 83}, {"id": 224182, "mc": 212, "oc": 48}], "ceny": [{"id": 79377, "mc": 1555, "oc": 60}, {"id": 91732, "mc": 140, "oc": 20}], "cela": [{"id": 81849, "mc": 38, "oc": 4}], "cebu": [{"id": 86871, "mc": 1423, "oc": 154}], "centropoli": [{"id": 87818, "mc": 65, "oc": 13}], "cellar": [{"id": 89840, "mc": 6136, "oc": 1234}], "cephalofair": [{"id": 90688, "mc": 3663, "oc": 783}], "celled": [{"id": 93694, "mc": 165, "oc": 49}], "centercloud": [{"id": 93983, "mc": 174, "oc": 6}], "centrum": [{"id": 95564, "mc": 1206, "oc": 137}], "centraal": [{"id": 96290, "mc": 5, "oc": 3}, {"id": 189009, "mc": 790, "oc": 54}], "ceniza": [{"id": 96740, "mc": 23, "oc": 4}], "celebration": [{"id": 98107, "mc": 1153, "oc": 36}, {"id": 101903, "mc": 1579, "oc": 196}, {"id": 124428, "mc": 696, "oc": 99}, {"id": 147298, "mc": 3549, "oc": 339}, {"id": 195705, "mc": 9545, "oc": 3544}, {"id": 205230, "mc": 59141, "oc": 6616}, {"id": 240913, "mc": 1519, "oc": 92}], "cei": [{"id": 100591, "mc": 427, "oc": 50}], "cerchi": [{"id": 100866, "mc": 9439, "oc": 1211}, {"id": 151257, "mc": 2638, "oc": 114}, {"id": 160364, "mc": 48, "oc": 7}], "celular": [{"id": 101589, "mc": 13460, "oc": 187}], "cereal": [{"id": 106626, "mc": 40680, "oc": 9776}, {"id": 119508, "mc": 1168, "oc": 114}, {"id": 227618, "mc": 513, "oc": 67}], "ceylon": [{"id": 108544, "mc": 13653, "oc": 942}], "censored": [{"id": 112984, "mc": 9686, "oc": 1216}], "centaur": [{"id": 113635, "mc": 414, "oc": 104}], "cexplorer": [{"id": 117368, "mc": 275, "oc": 40}], "cel": [{"id": 125770, "mc": 1959, "oc": 298}, {"id": 197245, "mc": 11, "oc": 2}, {"id": 197245, "mc": 11, "oc": 2}, {"id": 197245, "mc": 11, "oc": 2}, {"id": 221234, "mc": 333, "oc": 61}, {"id": 233966, "mc": 45134, "oc": 1433}, {"id": 248012, "mc": 122, "oc": 21}], "celor": [{"id": 127896, "mc": 30649, "oc": 4334}, {"id": 231357, "mc": 1065, "oc": 73}], "cercana": [{"id": 128045, "mc": 191, "oc": 36}], "cease": [{"id": 128161, "mc": 82, "oc": 19}], "ceasefire": [{"id": 135001, "mc": 7479, "oc": 2164}], "cercle": [{"id": 139466, "mc": 199, "oc": 24}, {"id": 139466, "mc": 199, "oc": 24}, {"id": 212768, "mc": 69330, "oc": 3507}, {"id": 217895, "mc": 1274, "oc": 57}], "ceramic": [{"id": 150196, "mc": 80, "oc": 12}], "cerberu": [{"id": 150588, "mc": 51, "oc": 19}, {"id": 164118, "mc": 1661, "oc": 193}, {"id": 245684, "mc": 347, "oc": 67}], "ceremonie": [{"id": 157520, "mc": 29, "oc": 8}], "ceremonial": [{"id": 157784, "mc": 1444, "oc": 119}], "cest": [{"id": 158269, "mc": 1395, "oc": 42}], "centaury": [{"id": 159046, "mc": 257, "oc": 30}], "cero": [{"id": 159810, "mc": 86, "oc": 17}, {"id": 245423, "mc": 1043, "oc": 99}], "ceazy": [{"id": 162084, "mc": 1146, "oc": 98}], "cedar": [{"id": 165696, "mc": 3168, "oc": 628}, {"id": 165696, "mc": 3168, "oc": 628}, {"id": 210057, "mc": 9126, "oc": 322}], "celebrated": [{"id": 175218, "mc": 2094, "oc": 16}], "celo": [{"id": 177076, "mc": 1658, "oc": 115}, {"id": 192803, "mc": 13469, "oc": 1003}], "centeral": [{"id": 181450, "mc": 74, "oc": 19}], "cellbit": [{"id": 182448, "mc": 194288, "oc": 9684}], "certainly": [{"id": 183411, "mc": 325, "oc": 41}], "celestopedia": [{"id": 191354, "mc": 14, "oc": 7}], "celestior": [{"id": 192599, "mc": 1079, "oc": 293}], "cephalopod": [{"id": 195833, "mc": 113, "oc": 13}], "cellula": [{"id": 199678, "mc": 114069, "oc": 1121}], "cena": [{"id": 200651, "mc": 27520, "oc": 2251}], "cesspit": [{"id": 205208, "mc": 28, "oc": 7}], "cerita": [{"id": 206158, "mc": 1891, "oc": 73}], "celerity": [{"id": 207958, "mc": 3387, "oc": 926}], "celinett": [{"id": 214780, "mc": 11165, "oc": 221}], "cestu": [{"id": 218060, "mc": 822, "oc": 67}], "certik": [{"id": 223525, "mc": 39127, "oc": 1021}], "ceomg": [{"id": 224405, "mc": 7980, "oc": 386}], "certaine": [{"id": 229456, "mc": 40, "oc": 17}], "cede": [{"id": 229667, "mc": 1897, "oc": 171}], "cerbi": [{"id": 230542, "mc": 67, "oc": 30}], "cefore": [{"id": 240681, "mc": 502, "oc": 44}], "cerchia": [{"id": 246413, "mc": 233, "oc": 71}], "cerdax": [{"id": 247719, "mc": 271, "oc": 49}]}