{"pp": [{"id": 1775, "mc": 5578, "oc": 332}, {"id": 125175, "mc": 34945, "oc": 10655}], "ppa": [{"id": 5851, "mc": 336, "oc": 10}], "ppc": [{"id": 12415, "mc": 1096, "oc": 39}, {"id": 237200, "mc": 10027, "oc": 353}], "ppl": [{"id": 16473, "mc": 800, "oc": 134}, {"id": 19240, "mc": 68, "oc": 20}, {"id": 29163, "mc": 141, "oc": 34}, {"id": 48825, "mc": 84, "oc": 26}, {"id": 58057, "mc": 1371, "oc": 251}, {"id": 64504, "mc": 2458, "oc": 59}, {"id": 76364, "mc": 74, "oc": 29}, {"id": 105107, "mc": 148, "oc": 38}, {"id": 135097, "mc": 177, "oc": 38}, {"id": 142123, "mc": 194, "oc": 39}, {"id": 146483, "mc": 143, "oc": 31}, {"id": 146786, "mc": 1729, "oc": 113}, {"id": 146932, "mc": 71, "oc": 27}, {"id": 153304, "mc": 17, "oc": 5}, {"id": 174465, "mc": 535, "oc": 54}, {"id": 176266, "mc": 2318, "oc": 118}, {"id": 179884, "mc": 387, "oc": 104}, {"id": 182291, "mc": 11, "oc": 6}, {"id": 194320, "mc": 155, "oc": 34}, {"id": 223824, "mc": 76, "oc": 14}, {"id": 225626, "mc": 35, "oc": 11}, {"id": 229420, "mc": 35, "oc": 7}, {"id": 229420, "mc": 35, "oc": 7}, {"id": 232340, "mc": 4973, "oc": 334}, {"id": 241156, "mc": 1171, "oc": 170}, {"id": 243804, "mc": 1761, "oc": 164}], "ppreciate": [{"id": 23521, "mc": 736, "oc": 75}, {"id": 23521, "mc": 736, "oc": 75}, {"id": 23521, "mc": 736, "oc": 75}], "ppp": [{"id": 31561, "mc": 178, "oc": 19}], "ppv": [{"id": 31882, "mc": 59, "oc": 7}, {"id": 205013, "mc": 9658, "oc": 1017}], "ppf": [{"id": 82551, "mc": 336, "oc": 41}, {"id": 176318, "mc": 575, "oc": 17}, {"id": 176318, "mc": 575, "oc": 17}], "ppt": [{"id": 111869, "mc": 491, "oc": 120}, {"id": 111869, "mc": 491, "oc": 120}], "ppsr": [{"id": 165355, "mc": 4953, "oc": 1039}], "ppg": [{"id": 180321, "mc": 46, "oc": 12}], "ppsw": [{"id": 185316, "mc": 1180, "oc": 141}], "pppandasnft": [{"id": 206662, "mc": 1066, "oc": 50}], "ppppu": [{"id": 209903, "mc": 1474, "oc": 180}]}